Workbook

Sheet Overview
A1: TRIBE DIGITAL BOILER MODEL
A2: Economic model for modular data centre heat recovery
A3: Version 3.1 - Dynamic Capex | January 2026
A5: HOW TO USE THIS MODEL
A7: Step 1 | B7: Configure Hardware | C7: Go to '0. Rack Profile' and select your chipset (dropdown in B6) and cooling method (dropdown in B17). Optionally adjust the module IT capacity target (B36).
A8: Step 2 | B8: Review Module Specs | C8: Check '1. Module Criteria' to see the resulting module specifications. Enable/disable heat pump (B15) and set output temperature if needed.
A9: Step 3 | B9: Check Capex | C9: Review '2. Module Capex' - costs are calculated automatically from your hardware choices. Adjust Reference Data rates if needed.
A10: Step 4 | B10: Select Customer Process | C10: Go to '5. Buyer Profile' and select an industrial process from the dropdown (B11). The model calculates how many modules are needed.
A11: Step 5 | B11: Review System Economics | C11: Check '6. System Capex' for total investment, '9. System P&L' for revenue and profit analysis.
A12: Step 6 | B12: Adjust Assumptions | C12: Fine-tune costs in '11. Reference Data' (yellow cells). All downstream calculations update automatically.
A14: MODEL STRUCTURE
A16: Sheet | B16: Purpose | C16: Key Features
A17: 0. Rack Profile | B17: Hardware config | C17: Chipset, cooling method, rack density, heat capture
A18: 1. Module Criteria | B18: Module specs | C18: Heat pump config, thermal output, heat pricing
A19: 2. Module Capex | B19: Module capital cost | C19: Dynamic from Rack Profile - enclosure, cooling, power, thermal, monitoring
A20: 3. Module Opex | B20: Module operating cost | C20: Electricity, maintenance, insurance
A21: 4. Module Flow | B21: Module hydraulics | C21: Flow rates, pipe sizing
A22: 5. Buyer Profile | B22: Customer matching | C22: Process selection, modules required, heat balance, rejection sizing
A23: 6. System Capex | B23: System capital | C23: Total investment including rejection equipment
A24: 7. System Opex | B24: System operating cost | C24: Including rejection running costs
A25: 8. System Flow | B25: System hydraulics | C25: Supply vs demand, utilisation, constraints
A26: 9. System P&L | B26: Profit & loss | C26: Revenue (compute + heat), costs, margins, payback
A27: 11. Reference Data | B27: Lookup tables | C27: Hardware costs, chipset specs, rejection rates, process ΔT
A28: 12. Process Library | B28: Process database | C28: 42 industrial heat processes with source citations
A30: KEY CONCEPTS
A32: BYOGPU Model | B32: Customers bring their own GPUs - capex covers infrastructure only, not compute hardware
A33: Thermal vs Flow | B33: Low ΔT processes become flow-constrained, needing more modules than thermal demand alone
A34: Heat Rejection | B34: Equipment sized for 100% rejection (buyer offline); opex based on actual excess
A35: Cooling Premium | B35: DTC +15%, Single-phase immersion +25%, Two-phase +40% vs air-cooled
A36: Dynamic Capex | B36: Module costs auto-calculate from Rack Profile - change chipset/cooling, capex updates
A38: DATA FLOW
A40: Rack Profile → Module Criteria → Module Capex/Opex → Buyer Profile → System Capex/Opex/P&L
A42: INPUT CONVENTIONS
A44: Yellow cells | B44: Example | C44: Adjustable inputs - safe to modify
A45: Blue headers | B45: Example | C45: Section headers - do not edit
A46: White cells | B46: Example | C46: Calculated values - do not edit
A48: KEY INPUTS QUICK REFERENCE
A50: Location | B50: Input | C50: Options
A51: Rack Profile B6 | B51: Chipset | C51: NVIDIA H100/H200/B200, AMD MI300X, Intel Gaudi 3
A52: Rack Profile B17 | B52: Cooling method | C52: DTC, Single-Phase Immersion, Two-Phase Immersion, RDHX
A53: Rack Profile B36 | B53: Module size | C53: IT capacity target in kW (default 250)
A54: Module Criteria B15 | B54: Heat pump | C54: 1 = enabled, 0 = disabled
A55: Module Criteria B29 | B55: Heat price | C55: £/MWh for heat sales
A56: Buyer Profile B11 | B56: Process | C56: Select from dropdown (42 options)
A57: Reference Data B71+ | B57: Hardware costs | C57: All yellow cells - adjust to your pricing

Sheet Agent Context
A1: AGENT CONTEXT
A2: Context and guidelines for AI agents working on this model
A4: BUSINESS CONTEXT
A6: Business Model | B6: TRIBE operates 'digital boilers' - modular data centres co-located on industrial sites that capture waste heat from GPU compute and sell it to industrial partners.
A7: BYOGPU | B7: Customers bring their own GPUs - TRIBE provides infrastructure only. Capex excludes compute hardware costs.
A8: Heat Capture | B8: Liquid cooling (DTC or immersion) captures 75-98% of server waste heat at 45-57°C. Heat pumps lift this to 70-90°C for industrial use.
A9: Revenue Streams | B9: 1) Compute hosting fees (£/kW/month), 2) Heat sales to industrial buyer (£/MWh)
A10: Target Customers | B10: Industrial processes requiring low-grade heat: pasteurisation, CIP systems, district heating, commercial laundry, swimming pools, HVAC
A12: MODEL ARCHITECTURE
A14: Data Flow | B14: Rack Profile → Module Criteria → Module Capex/Opex/Flow → Buyer Profile → System Capex/Opex/Flow/P&L
A15: Rack Profile | B15: INPUTS: Chipset (dropdown B6), Cooling method (dropdown B17), Module IT target (B36). OUTPUTS: Rack density, heat capture rate, capex premium.
A16: Module Criteria | B16: INPUTS: Heat pump toggle (B15), HP output temp (B16), Heat pricing (B27-B29). OUTPUTS: Per-module thermal output, COP.
A17: Module Capex | B17: DYNAMIC CALCULATION from Rack Profile. References costs in '11. Reference Data' rows 71-105. Conditional DTC vs Immersion blocks.
A18: Buyer Profile | B18: INPUT: Process selection dropdown (B11) from Process Library. OUTPUTS: Modules required, binding constraint (thermal vs flow), heat rejection sizing.
A19: System Sheets | B19: Aggregate module-level calculations × number of modules. Add shared infrastructure, rejection equipment, integration costs.
A20: Reference Data | B20: LOOKUP TABLES: Rejection infrastructure (rows 9-16), Cooling characteristics (rows 22-27), Chipsets (rows 33-38), Hardware capex (rows 71-105).
A21: Process Library | B21: DATABASE of 42 industrial processes with temp, thermal load, operating hours, ΔT, source citations. Feeds Buyer Profile dropdown.
A23: KEY TECHNICAL CONCEPTS
A25: Thermal vs Flow Constraint | B25: Low ΔT processes (e.g. pasteurisation, 5°C) become FLOW-constrained - need more modules than thermal demand alone. High ΔT processes (e.g. district heating, 30°C) are THERMAL-constrained.
A26: Heat Pump Thermodynamics | B26: Q_hot = Q_cold × COP/(COP-1). Electrical input = Q_hot/COP. COP decreases with higher temperature lift (source→sink).
A27: Heat Rejection Sizing | B27: CAPEX sized for 100% rejection (worst case - buyer goes offline). OPEX based on ACTUAL excess heat during normal operation.
A28: Cooling Method Trade-offs | B28: DTC: 75% capture, 57.5°C, +15% capex, larger footprint. Immersion: 95-98% capture, 50-55°C, +25-40% capex, denser packing.
A29: Rack Thermal Limits | B29: DTC: 80kW/rack, Single-phase immersion: 100kW/rack, Two-phase: 120kW/rack. Determines GPU density and module footprint.
A31: FORMULA CONVENTIONS
A33: Cross-sheet references | B33: Use full sheet names in quotes, e.g. ='0. Rack Profile'!B37
A34: Conditional blocks | B34: DTC vs Immersion costs use IF(B6="Direct-to-Chip (DTC)",...) pattern
A35: Unit conversions | B35: kWh to MWh: divide by 1000. Annual hours: 8760. Heat: kWth (thermal kilowatts).
A36: Currency | B36: All values in GBP (£). Format: £#,##0 for whole numbers, £#,##0.00 for decimals.
A37: Percentages | B37: Store as decimals (0.15 not 15%), format as 0.0% for display.
A39: KEY CELL REFERENCES
A41: Cell | B41: Description | C41: Notes
A42: 0. Rack Profile!B6 | B42: Chipset selection (dropdown) | C42: Drives TDP, density, cost assumptions
A43: 0. Rack Profile!B17 | B43: Cooling method selection (dropdown) | C43: Drives heat capture rate, PUE, capex, source ΔT
A44: 0. Rack Profile!B23 | B44: PUE by cooling method | C44: From Reference Data lookup. Drives infrastructure power.
A45: 0. Rack Profile!B37 | B45: Racks per module | C45: Calculated from space constraints
A46: 0. Rack Profile!B40 | B46: Module IT capacity (kW) | C46: TDP × racks per module
A47: 0. Rack Profile!B43 | B47: Captured heat (kWth) | C47: IT capacity × heat capture rate
A49: 1. Module Criteria!B15 | B49: Heat pump enabled (1/0) | C49: Toggles HP capex/opex calculations
A50: 1. Module Criteria!B16 | B50: Heat pump output temp (°C) | C50: Input for COP calculation
A51: 1. Module Criteria!B17 | B51: COP (Carnot-based) | C51: 0.5×(T_out+273)/ΔT lift. Dynamic by temps.
A52: 1. Module Criteria!B21 | B52: Module thermal output (kWth) | C52: Captured × COP/(COP-1)
A54: 4. Module Flow!B11 | B54: Source loop ΔT (°C) | C54: Lookup by cooling method (3-15°C). Was hardcoded 10°C.
... A78: 11. Reference Data!E23-E27 | B78: Source ΔT by cooling method | C78: DTC=10, Single=6, Two=3, RDHX=12, Air=15°C
A81: CURRENT MODEL ARCHITECTURE
A83: Module Sizing Logic | B83: Modules sized on THERMAL capacity only (not flow). Module count = CEIL(heat_demand / module_output).
A84: Flow Handling | B84: Flow deficits handled via hydraulic augmentation (pumps, mixing valves) at ~£8k vs £250k+ per extra module.
A85: ΔT Chain | B85: Cooling Method → Source ΔT (variable) → Source Flow. Module Sink ΔT (fixed 10°C) vs Process ΔT (variable) → Flow Deficit → Hydraulics.
A86: COP Calculation | B86: Carnot-based: COP = 0.5 × (T_out + 273) / (T_out - T_source). Dynamic based on actual temperatures.
A87: Infrastructure Power | B87: Derived from PUE by cooling method (PUE - 1). Not hardcoded.
A90: KEY DESIGN DECISIONS
A92: Decision | B92: Rationale
A93: Thermal-only module sizing | B93: Physics: Q=ṁ×Cp×ΔT means sufficient heat can always match flow via blending. Flow is hydraulic cost, not module constraint.
A94: Fixed module sink ΔT (10°C) | B94: Standard module design. Process ΔT varies (5-30°C). Mismatch creates flow deficit handled by augmentation.
A95: Variable source ΔT by cooling | B95: Two-phase immersion has lower ΔT (3°C) vs air cooling (15°C). Affects source-side flow and pump sizing.
A96: Discrete pump sizing (25 m³/hr) | B96: Standard commercial pump size. Count = ROUNDUP(deficit/25). Provides clear BOM and capex.
A97: COP varies with temperature | B97: Real HP performance. Higher lift = lower COP = more electricity. Carnot efficiency ~50% typical.
A100: CHANGE LOG (January 2026)
A102: Change | B102: Impact
A103: COP: Hardcoded 4 → Carnot formula | B103: COP now 3-6 depending on temps. Affects HP electricity and thermal output.
A104: Module sizing: MAX(thermal,flow) → thermal only | B104: Pasteurisation: 5 modules → 3 modules (-40% capex). Flow deficit via pumps.
A105: Infrastructure power: 5% → PUE-based | B105: DTC: 2% overhead. Immersion: 5-40%. Reflects actual cooling method efficiency.
A106: Source ΔT: Hardcoded 10°C → cooling method lookup | B106: Two-phase: 3°C. Air: 15°C. Affects source flow calculations.
A107: Added hydraulic augmentation | B107: New capex/opex sections for pumps, mixing valves when flow deficit exists.
A108: Added discrete pump sizing | B108: Pump count, capacity, verification. Flows through BOM and capex.
A109: Fixed broken references | B109: Module Opex maintenance/insurance, Buyer Profile heat balance, System P&L profit formulas.
A110: Added formula documentation (F/G/H columns) | B110: All calculation sheets now have Intent, Explanation, and Dependents columns.
A112: DOCUMENTATION STRUCTURE
A114: Column F: Intent | B114: Why this cell exists - business/engineering purpose
A115: Column G: Explanation | B115: What the formula/value does technically
A116: Column H: Dependents | B116: Cells that directly reference this cell
A117: Purpose
A118: Formula documentation | B118: Every calculation sheet (0-11) has columns F and G for documentation. This enables traceability and reduces errors during model updates.
A119: Dependency tracking | B119: Direct dependents only (not cascading). Shows which downstream calculations would be affected if this cell changes.
A121: Maintenance Guidelines
A122: When adding a new formula | B122: Add explanation in column F describing the formula's purpose. Check if any cells reference this new cell and update their Dependents.
A123: When modifying a formula | B123: Update the explanation if the logic changes. Review dependents to ensure downstream calculations still make sense.
A124: When deleting a cell | B124: Check Dependents column first. If any cells reference this one, update or remove those formulas before deleting.
A126: Format Conventions
A127: Intent column | B127: Brief statement of purpose (5-15 words). Focus on WHY not WHAT.
A128: Explanation column | B128: Technical description of formula logic or value source.
A129: Dependents column | B129: Format: Sheet!Cell - Description. Max 10 entries shown.

Sheet 0. Rack Profile
A1: RACK PROFILE | F1: Intent | G1: Explanation | H1: Dependents
A2: Define module hardware configuration - chipset and cooling approach | F2: Define GPU hardware to determine power and cooling requirements | G2: Row label only
A4: CHIPSET CONFIGURATION
A6: Chipset type | B6: NVIDIA H100 | F6: Define GPU hardware to determine power and cooling requirements | G6: Text value for Chipset type | H6: 0. Rack Profile!B9 - TDP per chip (W); 0. Rack Profile!B10 - Chips per server; 0. Rack Profile!B12 - Max junction temp (°C); 2. Module Capex!B5 - Chipset; 5. Buyer Profile!B5 - Chipset; 6. System Capex!B5 - Chipset; 7. System Opex!B5 - Chipset; 8. System Flow!B5 - Chipset; 9. System P&L!B8 - Chipset
A8: Chipset Specifications | F8: Define GPU hardware to determine power and cooling requirements | G8: Row label only
A9: TDP per chip (W) | B9: =IF(B6="NVIDIA H100",700,IF(B6="NVIDIA H200",700,IF(B6="NVIDIA B200",1000,IF(B6="AMD MI300X",750,IF(B6="Intel Gaudi 3",600,500))))) | C9: Thermal Design Power | F9: Establish base power draw for thermal calculations | G9: Conditional logic for TDP per chip (W) | H9: 0. Rack Profile!B11 - Server power (kW)
A10: Chips per server | B10: =IF(B6="NVIDIA H100",8,IF(B6="NVIDIA H200",8,IF(B6="NVIDIA B200",8,IF(B6="AMD MI300X",8,IF(B6="Intel Gaudi 3",8,8))))) | C10: Typical GPU count per node | F10: Configure server density for rack power calculations | G10: Conditional logic for Chips per server | H10: 0. Rack Profile!B11 - Server power (kW); 0. Rack Profile!B30 - GPUs per rack
A11: Server power (kW) | B11: =B9*B10/1000*1.15 | C11: Chip TDP × count × 1.15 (overhead) | F11: Calculate total server power including overhead for sizing | G11: Calculated from upstream values for Server power (kW) | H11: 0. Rack Profile!B29 - Servers per rack; 0. Rack Profile!B31 - Actual rack power (kW)
A12: Max junction temp (°C) | B12: =IF(B6="NVIDIA H100",83,IF(B6="NVIDIA H200",83,IF(B6="NVIDIA B200",85,IF(B6="AMD MI300X",90,IF(B6="Intel Gaudi 3",95,85))))) | C12: Chip thermal limit | F12: Define thermal limits to ensure safe GPU operation | G12: Conditional logic for Max junction temp (°C) | H12: 0. Rack Profile!B13 - Recommended coolant inlet (°C)
A13: Recommended coolant inlet (°C) | B13: =B12-25 | C13: Target 25°C below Tj max | F13: Set cooling system design temperature | G13: Calculated from upstream values for Recommended coolant inlet (°C)
A15: COOLING APPROACH
A17: Cooling method | B17: Direct-to-Chip (DTC) | F17: Select cooling technology to determine heat capture and costs | G17: Text value for Cooling method | H17: 0. Rack Profile!B20 - Heat capture rate (%); 0. Rack Profile!B21 - Capture temperature (°C); 0. Rack Profile!B22 - Coolant type; 0. Rack Profile!B23 - PUE contribution; 0. Rack Profile!B24 - Capex premium vs air-cooled (%); 0. Rack Profile!B25 - Rack thermal limit (kW/rack); 2. Module Capex!B6 - Cooling method; 4. Module Flow!B11 - Source loop ΔT (°C); 5. Buyer Profile!B6 - Cooling method; 6. System Capex!B6 - Cooling method; ... and 3 more
A19: Cooling Method Characteristics | F19: Select cooling technology to determine heat capture and costs | G19: Row label only
A20: Heat capture rate (%) | B20: =IF(B17="Direct-to-Chip (DTC)",0.75,IF(B17="Single-Phase Immersion",0.95,IF(B17="Two-Phase Immersion",0.98,IF(B17="Rear Door Heat Exchanger",0.5,0.05)))) | C20: Fraction of IT heat captured to liquid | F20: Quantify recoverable heat for revenue calculations | G20: Conditional logic for Heat capture rate (%) | H20: 0. Rack Profile!B43 - Captured heat (kWth); 0. Rack Profile!B45 - Residual heat to air (kWth); 0. Rack Profile!B63 - Total heat output (per kW IT); 1. Module Criteria!B10 - Heat capture rate (%)
A21: Capture temperature (°C) | B21: =IF(B17="Direct-to-Chip (DTC)",57.5,IF(B17="Single-Phase Immersion",50,IF(B17="Two-Phase Immersion",55,IF(B17="Rear Door Heat Exchanger",45,35)))) | C21: Typical coolant outlet temperature | F21: Determine heat quality for buyer matching | G21: Conditional logic for Capture temperature (°C) | H21: 0. Rack Profile!B44 - Capture temperature (°C); 0. Rack Profile!B49 - Heat capture quality; 0. Rack Profile!B50 - Heat pump requirement; 0. Rack Profile!B51 - Recommended HP output (°C); 0. Rack Profile!B52 - Estimated COP at recommended output; 0. Rack Profile!B60 - Temperature lift (K); 1. Module Criteria!B12 - Capture temperature (°C); 8. System Flow!B7 - Capture temperature (°C)
A22: Coolant type | B22: =IF(B17="Direct-to-Chip (DTC)","Water/Glycol",IF(B17="Single-Phase Immersion","Dielectric fluid",IF(B17="Two-Phase Immersion","Fluorocarbon",IF(B17="Rear Door Heat Exchanger","Water/Glycol","Air")))) | F22: Specify fluid for equipment selection | G22: Conditional logic for Coolant type
A23: PUE contribution | B23: =IF(B17="Direct-to-Chip (DTC)",1.05,IF(B17="Single-Phase Immersion",1.03,IF(B17="Two-Phase Immersion",1.02,IF(B17="Rear Door Heat Exchanger",1.1,1.4)))) | C23: Cooling system efficiency factor | F23: Model infrastructure efficiency for opex calculations | G23: Conditional logic for PUE contribution | H23: 3. Module Opex!B6 - Infrastructure power (from PUE)
A24: Capex premium vs air-cooled (%) | B24: =IF(B17="Direct-to-Chip (DTC)",15,IF(B17="Single-Phase Immersion",25,IF(B17="Two-Phase Immersion",40,IF(B17="Rear Door Heat Exchanger",10,0)))) | F24: Account for cooling technology cost differences | G24: Conditional logic for Capex premium vs air-cooled (%) | H24: 2. Module Capex!B59 - Premium rate (%)
A25: Rack thermal limit (kW/rack) | B25: =IF(B17="Direct-to-Chip (DTC)",80,IF(B17="Single-Phase Immersion",100,IF(B17="Two-Phase Immersion",120,IF(B17="Rear Door Heat Exchanger",40,20)))) | C25: Max power per 42U rack | F25: Set rack density constraint for module sizing | G25: Conditional logic for Rack thermal limit (kW/rack) | H25: 0. Rack Profile!B29 - Servers per rack; 0. Rack Profile!B32 - Rack thermal utilisation (%)
A27: RACK CONFIGURATION
A29: Servers per rack | B29: =ROUNDDOWN(B25/B11,0) | C29: Rack thermal limit ÷ server power | F29: Calculate achievable density within thermal limits | G29: Rounded calculation for Servers per rack | H29: 0. Rack Profile!B30 - GPUs per rack; 0. Rack Profile!B31 - Actual rack power (kW); 0. Rack Profile!B38 - Servers per module
A30: GPUs per rack | B30: =B29*B10 | C30: Servers per rack × chips per server | F30: Compute total GPU capacity per rack | G30: Calculated from upstream values for GPUs per rack | H30: 0. Rack Profile!B39 - GPUs per module
A31: Actual rack power (kW) | B31: =B29*B11 | C31: May be less than thermal limit | F31: Determine actual power for infrastructure sizing | G31: Calculated from upstream values for Actual rack power (kW) | H31: 0. Rack Profile!B32 - Rack thermal utilisation (%); 0. Rack Profile!B37 - Racks per module; 0. Rack Profile!B40 - Actual module IT capacity (kW)
A32: Rack thermal utilisation (%) | B32: =B31/B25 | C32: Actual vs limit | F32: Assess how well rack capacity is used | G32: Calculated from upstream values for Rack thermal utilisation (%)
A34: MODULE SUMMARY
A36: Module IT capacity target (kW) | B36: 250 | C36: Design target - adjust as needed | F36: Define standardised module size for business model | G36: Input parameter: Module IT capacity target (kW) | H36: 0. Rack Profile!B37 - Racks per module
A37: Racks per module | B37: =ROUNDUP(B36/B31,0) | C37: To meet capacity target | F37: Calculate rack count to meet module capacity target | G37: Rounded calculation for Racks per module | H37: 0. Rack Profile!B38 - Servers per module; 0. Rack Profile!B39 - GPUs per module; 0. Rack Profile!B40 - Actual module IT capacity (kW); 2. Module Capex!B7 - Racks per module
A38: Servers per module | B38: =B37*B29 | F38: Aggregate compute capacity at module level | G38: Calculated from upstream values for Servers per module | H38: 2. Module Capex!B8 - Servers per module
A39: GPUs per module | B39: =B37*B30 | F39: Aggregate compute capacity at module level | G39: Calculated from upstream values for GPUs per module | H39: 2. Module Capex!B69 - Capex per GPU (£/GPU); 5. Buyer Profile!B7 - GPUs per module; 6. System Capex!B7 - GPUs per module; 7. System Opex!B7 - GPUs per module
A40: Actual module IT capacity (kW) | B40: =B37*B31 | C40: May differ slightly from target | F40: Define standardised module size for business model | G40: Calculated from upstream values for Actual module IT capacity (kW) | H40: 0. Rack Profile!B43 - Captured heat (kWth); 0. Rack Profile!B45 - Residual heat to air (kWth); 0. Rack Profile!B68 - Heat delivered (MWh/yr); 1. Module Criteria!B5 - Module IT capacity (kW); 2. Module Capex!B9 - Module IT capacity (kW); 5. Buyer Profile!B8 - Module IT capacity (kW); 6. System Capex!B48 - Capex per IT kW (£/kW)
A42: Heat Output | F42: Calculate annual heat sales volume
A43: Captured heat (kWth) | B43: =B40*B20 | C43: Available for heat recovery | F43: Calculate heat available for sale to buyers | G43: Calculated from upstream values for Captured heat (kWth) | H43: 0. Rack Profile!B69 - HP electricity (MWh/yr); 2. Module Capex!B10 - Captured heat (kWth)
A44: Capture temperature (°C) | B44: =B21 | F44: Determine heat quality for buyer matching | G44: Formula: Capture temperature (°C)
A45: Residual heat to air (kWth) | B45: =B40*(1-B20) | C45: Requires conventional cooling | F45: Identify heat requiring rejection (cost) | G45: Calculated from upstream values for Residual heat to air (kWth)
A47: HEAT RECOVERY ASSESSMENT
A49: Heat capture quality | B49: =IF(B21>=55,"HIGH - Suitable for process heat",IF(B21>=45,"MEDIUM - District heating suitable","LOW - Limited applications")) | F49: Classify heat grade for buyer matching | G49: Conditional logic for Heat capture quality
A50: Heat pump requirement | B50: =IF(B21>=70,"Optional - direct use possible",IF(B21>=50,"Recommended for industrial use","Required for most applications")) | F50: Determine if temperature boost needed for applications | G50: Conditional logic for Heat pump requirement | H50: 0. Rack Profile!B52 - Estimated COP at recommended output
A51: Recommended HP output (°C) | B51: =IF(B21>=70,B21,IF(B21>=50,90,80)) | F51: Model parameter | G51: Conditional logic for Recommended HP output (°C) | H51: 0. Rack Profile!B52 - Estimated COP at recommended output; 0. Rack Profile!B57 - Target output temperature (°C)
A52: Estimated COP at recommended output | B52: =IF(B50="Optional - direct use possible","-",MAX('11. Reference Data'!B111,MIN('11. Reference Data'!B112,ROUND('11. Reference Data'!B110*(B51+273.15)/(B51-B21),2)))) | C52: Carnot-based estimate | F52: Calculate heat pump efficiency for economics | G52: Conditional logic for Estimated COP at recommended output
A54: HEAT PUMP ECONOMICS
A55: Trade-off analysis: capture efficiency vs. HP operating cost | F55: Financial input or calculation | G55: Row label only
A57: Target output temperature (°C) | B57: =B51 | C57: From heat recovery assessment | F57: Temperature parameter for thermal design | G57: Formula: Target output temperature (°C) | H57: 0. Rack Profile!B60 - Temperature lift (K); 0. Rack Profile!B61 - COP at this lift
A58: Electricity price (£/kWh) | B58: 0.18 | C58: Grid electricity rate | F58: Financial input or calculation | G58: Input parameter: Electricity price (£/kWh) | H58: 0. Rack Profile!B64 - HP electricity cost (£/kWth·hr); 0. Rack Profile!B70 - HP electricity cost (£/yr)
A60: Temperature lift (K) | B60: =B57-B21 | C60: Output temp - capture temp | F60: Define upgrade required from source to delivery temp | G60: Calculated from upstream values for Temperature lift (K) | H60: 0. Rack Profile!B61 - COP at this lift
A61: COP at this lift | B61: =IF(B60<=0,"-",MAX('11. Reference Data'!B111,MIN('11. Reference Data'!B112,ROUND('11. Reference Data'!B110*(B57+273.15)/B60,2)))) | C61: Carnot-based estimate | F61: Calculate heat pump efficiency for economics | G61: Conditional logic for COP at this lift | H61: 0. Rack Profile!B62 - HP electricity per kWth captured; 0. Rack Profile!B63 - Total heat output (per kW IT)
A62: HP electricity per kWth captured | B62: =IF(B61="-","-",ROUND(1/(B61-1),3)) | C62: kWh elec per kWh heat lifted | F62: Model heat pump operating cost | G62: Conditional logic for HP electricity per kWth captured | H62: 0. Rack Profile!B64 - HP electricity cost (£/kWth·hr); 0. Rack Profile!B69 - HP electricity (MWh/yr)
A63: Total heat output (per kW IT) | B63: =IF(B61="-",B20,ROUND(B20*B61/(B61-1),3)) | C63: Captured × COP/(COP-1) | F63: Calculate annual heat sales volume | G63: Conditional logic for Total heat output (per kW IT) | H63: 0. Rack Profile!B68 - Heat delivered (MWh/yr)
A64: HP electricity cost (£/kWth·hr) | B64: =IF(B62="-","-",ROUND(B62*B58,4)) | C64: Marginal cost to deliver heat | F64: Model heat pump operating cost | G64: Conditional logic for HP electricity cost (£/kWth·hr)
A66: Module Annual Analysis | F66: Model parameter | G66: Row label only
A67: Annual operating hours | B67: 8000 | C67: Typical utilisation | F67: Model parameter | G67: Input assumption: Annual operating hours | H67: 0. Rack Profile!B68 - Heat delivered (MWh/yr); 0. Rack Profile!B69 - HP electricity (MWh/yr)
A68: Heat delivered (MWh/yr) | B68: =IF(B63="-","-",ROUND(B40*B63*B67/1000,0)) | C68: Per module | F68: Calculate annual heat sales volume | G68: Conditional logic for Heat delivered (MWh/yr)
A69: HP electricity (MWh/yr) | B69: =IF(B62="-",0,ROUND(B43*B62*B67/1000,0)) | C69: Per module | F69: Model heat pump operating cost | G69: Conditional logic for HP electricity (MWh/yr) | H69: 0. Rack Profile!B70 - HP electricity cost (£/yr)
A70: HP electricity cost (£/yr) | B70: =B69*1000*B58 | C70: Per module | F70: Model heat pump operating cost | G70: Calculated from upstream values for HP electricity cost (£/yr)
A73: COOLING METHOD COMPARISON
A75: Method | B75: Capture % | C75: Temp °C | D75: Lift to 90°C | E75: COP | F75: Model parameter | G75: Text value for Method | H75: Heat out/kW IT
A76: Direct-to-Chip (DTC) | B76: 75% | C76: 57.5 | D76: 32.5K | E76: 4.4 | F76: Model parameter | G76: Text value for Direct-to-Chip (DTC) | H76: 97%
A77: Single-Phase Immersion | B77: 95% | C77: 50 | D77: 40K | E77: 3.8 | F77: Model parameter | G77: Text value for Single-Phase Immersion | H77: 128%
A78: Two-Phase Immersion | B78: 98% | C78: 55 | D78: 35K | E78: 4.2 | F78: Model parameter | G78: Text value for Two-Phase Immersion | H78: 128%
A79: Rear Door Heat Exchanger | B79: 50% | C79: 45 | D79: 45K | E79: 3.4 | F79: Model parameter | G79: Text value for Rear Door Heat Exchanger | H79: 70%
A81: KEY INSIGHT: | G81: Row label only
A82: Immersion captures more heat but requires more HP electricity due to lower capture temperature. | F82: Determine heat quality for buyer matching | G82: Row label only
A83: DTC offers the best balance of capture efficiency and HP operating cost for high-temp applications. | F83: Financial input or calculation | G83: Row label only

Sheet 1. Module Criteria
A1: MODULE CRITERIA | F1: Intent | G1: Explanation | H1: Dependents
A2: Hardware specifications and configuration for a single digital boiler module | F2: Model parameter | G2: Row label only
A4: COMPUTE SPECIFICATIONS
A5: Module IT capacity (kW) | B5: ='0. Rack Profile'!B40 | C5: From Rack Profile (actual) | D5: Standard MDC module size | F5: Pull standardised module size for consistent sizing | G5: Pulls value from 0. Rack Profile!B40 | H5: 1. Module Criteria!B11 - Captured heat (kWth); 3. Module Opex!B7 - Infrastructure power cost (£/yr); 5. Buyer Profile!B65 - Total IT capacity (kW); 9. System P&L!B12 - Module IT capacity (kW)
A6: Compute rate (£/kW/month) | B6: 150 | D6: Colocation pricing | F6: Financial input or calculation | G6: Input parameter: Compute rate (£/kW/month) | H6: 9. System P&L!B13 - Rack rate (£/kW/month)
A7: Target utilisation rate (%) | B7: 0.9 | D7: Steady-state capacity utilisation | F7: Model realistic capacity usage for revenue | G7: Input parameter: Target utilisation rate (%) | H7: 1. Module Criteria!B24 - Annual heat output (MWh); 3. Module Opex!B7 - Infrastructure power cost (£/yr); 3. Module Opex!B9 - Heat pump electricity (£/yr); 5. Buyer Profile!B92 - Cooling infrastructure (kW); 9. System P&L!B15 - Utilisation assumption (%)
A9: HEAT CAPTURE SPECIFICATIONS
A10: Heat capture rate (%) | B10: ='0. Rack Profile'!B20 | C10: From Rack Profile (cooling method) | D10: % of IT load captured via DTC cooling | F10: Reference thermal specifications from rack design | G10: Pulls value from 0. Rack Profile!B20 | H10: 1. Module Criteria!B11 - Captured heat (kWth)
A11: Captured heat (kWth) | B11: =B5*B10 | D11: Thermal output without heat pump | F11: Power or thermal capacity metric | G11: Calculated from upstream values for Captured heat (kWth) | H11: 1. Module Criteria!B18 - Heat pump capacity (kWth); 1. Module Criteria!B21 - Thermal output (kWth); 4. Module Flow!B9 - Thermal power (kWth)
A12: Capture temperature (°C) | B12: ='0. Rack Profile'!B21 | C12: From Rack Profile (cooling method) | D12: DTC cooling loop output temperature | F12: Temperature parameter for thermal design | G12: Pulls value from 0. Rack Profile!B21 | H12: 1. Module Criteria!B17 - Heat pump COP; 1. Module Criteria!B22 - Delivery temperature (°C); 4. Module Flow!B10 - Inlet temperature (°C); 5. Buyer Profile!B69 - Heat pump required?; 5. Buyer Profile!B70 - Temperature lift required (K)
A14: HEAT PUMP CONFIGURATION
A15: Heat pump enabled? | B15: 1 | D15: 1 = Yes, 0 = No | F15: Toggle heat pump for scenario analysis | G15: Flag enabled for Heat pump enabled? | H15: 1. Module Criteria!B17 - Heat pump COP; 1. Module Criteria!B21 - Thermal output (kWth); 1. Module Criteria!B22 - Delivery temperature (°C); 1. Module Criteria!B29 - Effective heat price (£/MWh); 2. Module Capex!B53 - Heat pump unit; 2. Module Capex!B54 - Heat pump installation; 2. Module Capex!B55 - Heat pump controls; 3. Module Opex!B9 - Heat pump electricity (£/yr); 3. Module Opex!B18 - Heat pump maintenance (£/yr)
A16: Heat pump output temperature (°C) | B16: 90 | D16: Delivery temperature to industrial partner | F16: Temperature parameter for thermal design | G16: Input parameter: Heat pump output temperature (°C) | H16: 1. Module Criteria!B17 - Heat pump COP; 1. Module Criteria!B22 - Delivery temperature (°C)
A17: Heat pump COP | B17: =IF(B15=0,"-",MAX('11. Reference Data'!B111,MIN('11. Reference Data'!B112,ROUND('11. Reference Data'!B110*(B16+273.15)/(B16-B12),2)))) | D17: Carnot-based: η × T_hot(K) / ΔT | F17: Calculate heat pump efficiency at operating conditions | G17: Conditional logic for Heat pump COP | H17: 1. Module Criteria!B21 - Thermal output (kWth); 3. Module Opex!B9 - Heat pump electricity (£/yr); 5. Buyer Profile!B73 - HP electrical demand (kW)
A18: Heat pump capacity (kWth) | B18: =B11 | D18: Sized to captured heat | F18: Define or calculate system capability | G18: Formula: Heat pump capacity (kWth) | H18: 2. Module Capex!B53 - Heat pump unit; 5. Buyer Profile!B72 - Total HP capacity (kWth)
A20: MODULE OUTPUT SUMMARY
A21: Thermal output (kWth) | B21: =IF(B15=1,IF(B17<=1,B11,B11*B17/(B17-1)),B11) | D21: With HP: includes compressor work (COP protected) | F21: Calculate total heat delivery including HP boost | G21: Conditional logic for Thermal output (kWth) | H21: 1. Module Criteria!B24 - Annual heat output (MWh); 3. Module Opex!B9 - Heat pump electricity (£/yr); 4. Module Flow!B19 - Thermal power delivered (kWth); 5. Buyer Profile!B28 - Module thermal capacity (kWth)
A22: Delivery temperature (°C) | B22: =IF(B15=1,B16,B12) | F22: Set required output temperature for buyer | G22: Conditional logic for Delivery temperature (°C) | H22: 4. Module Flow!B20 - Outlet temperature (°C); 5. Buyer Profile!B29 - Module delivery temp (°C); 8. System Flow!B20 - Delivery temperature (°C)
A23: Hours per year | B23: 8760 | D23: 24/7 operation | F23: Model parameter | G23: Input assumption: Hours per year | H23: 1. Module Criteria!B24 - Annual heat output (MWh); 3. Module Opex!B7 - Infrastructure power cost (£/yr); 3. Module Opex!B9 - Heat pump electricity (£/yr)
A24: Annual heat output (MWh) | B24: =B21*B23*B7/1000 | F24: Convert to annual volume for revenue calculation | G24: Calculated from upstream values for Annual heat output (MWh)
A26: HEAT PRICING
A27: Base heat price - no HP (£/MWh) | B27: 25 | D27: Low-temp heat (55-60°C) | F27: Set heat sales price assumption | G27: Input parameter: Base heat price - no HP (£/MWh) | H27: 1. Module Criteria!B29 - Effective heat price (£/MWh)
A28: Premium heat price - with HP (£/MWh) | B28: 40 | D28: High-temp heat (90°C) | F28: Set heat sales price assumption | G28: Input parameter: Premium heat price - with HP (£/MWh) | H28: 1. Module Criteria!B29 - Effective heat price (£/MWh)
A29: Effective heat price (£/MWh) | B29: =IF(B15=1,B28,B27) | F29: Set heat sales price assumption | G29: Conditional logic for Effective heat price (£/MWh) | H29: 9. System P&L!B20 - Heat price (£/MWh)
A30: Reference: Industrial gas price (£/MWh) | B30: 53 | D30: UK industrial gas benchmark | F30: Financial input or calculation | G30: Input parameter: Reference: Industrial gas price (£/MWh)

Sheet 2. Module Capex
A1: MODULE CAPEX | F1: Intent | G1: Explanation | H1: Dependents
A2: Capital expenditure for a single digital boiler module | B2: Calculated dynamically from Rack Profile inputs | F2: Model parameter | G2: Text value for Capital expenditure for a single digital boiler module
A4: CONFIGURATION SUMMARY
A5: Chipset | B5: ='0. Rack Profile'!B6 | F5: Model parameter | G5: Pulls value from 0. Rack Profile!B6
A6: Cooling method | B6: ='0. Rack Profile'!B17 | F6: Model parameter | G6: Pulls value from 0. Rack Profile!B17 | H6: 2. Module Capex!B19 - Cold plate kits; 2. Module Capex!B20 - CDU (base); 2. Module Capex!B21 - CDU (capacity scaling); 2. Module Capex!B22 - Manifolds & quick-connects; 2. Module Capex!B23 - Primary loop piping; 2. Module Capex!B27 - Immersion tanks; 2. Module Capex!B28 - Dielectric fluid (initial fill); 2. Module Capex!B29 - Fluid management system
A7: Racks per module | B7: ='0. Rack Profile'!B37 | F7: Model parameter | G7: Pulls value from 0. Rack Profile!B37 | H7: 2. Module Capex!B15 - Rack enclosures; 2. Module Capex!C15 - Rack enclosures; 2. Module Capex!B27 - Immersion tanks; 2. Module Capex!B28 - Dielectric fluid (initial fill); 2. Module Capex!B33 - Rack PDUs; 2. Module Capex!B47 - Per-rack monitoring
A8: Servers per module | B8: ='0. Rack Profile'!B38 | F8: Model parameter | G8: Pulls value from 0. Rack Profile!B38 | H8: 2. Module Capex!B19 - Cold plate kits; 2. Module Capex!B22 - Manifolds & quick-connects
A9: Module IT capacity (kW) | B9: ='0. Rack Profile'!B40 | F9: Define or calculate system capability | G9: Pulls value from 0. Rack Profile!B40 | H9: 2. Module Capex!B21 - CDU (capacity scaling); 2. Module Capex!B34 - Module power distribution; 2. Module Capex!B68 - Capex per IT kW (£/kW)
A10: Captured heat (kWth) | B10: ='0. Rack Profile'!B43 | F10: Power or thermal capacity metric | G10: Pulls value from 0. Rack Profile!B43 | H10: 2. Module Capex!B40 - Heat exchanger (capacity scaling)
A12: ENCLOSURE & STRUCTURE
A13: Container shell | B13: ='11. Reference Data'!B71 | C13: Fixed per module | F13: Cost modular enclosure structure | G13: Pulls value from 11. Reference Data!B71 | H13: 2. Module Capex!B16 - SUBTOTAL: ENCLOSURE
A14: Container fit-out | B14: ='11. Reference Data'!B72 | C14: Fixed per module | F14: Cost modular enclosure structure | G14: Pulls value from 11. Reference Data!B72
A15: Rack enclosures | B15: =B7*'11. Reference Data'!B73 | C15: =B7&" racks × £"&'11. Reference Data'!B73 | F15: Cost per-rack housing | G15: Calculated from upstream values for Rack enclosures | H15: 2. Module Capex!B16 - SUBTOTAL: ENCLOSURE
A16: SUBTOTAL: ENCLOSURE | B16: =SUM(B13:B15) | F16: Subtotal enclosure costs for module | G16: Sum of component values for SUBTOTAL: ENCLOSURE | H16: 2. Module Capex!B60 - Applied to base infrastructure; 2. Module Capex!B63 - Base infrastructure; 6. System Capex!B14 - Enclosure & structure
A18: DTC COOLING | B18: Applies when cooling method = DTC | F18: Section for DTC-specific equipment | G18: Section header
A19: Cold plate kits | B19: =IF(B6="Direct-to-Chip (DTC)",B8*'11. Reference Data'!B76,0) | C19: Servers × £250/server | F19: Cost DTC cooling hardware per server | G19: Conditional logic for Cold plate kits | H19: 2. Module Capex!B24 - SUBTOTAL: DTC COOLING
A20: CDU (base) | B20: =IF(B6="Direct-to-Chip (DTC)",'11. Reference Data'!B77,0) | C20: Fixed per module | F20: Cost coolant distribution unit | G20: Conditional logic for CDU (base)
A21: CDU (capacity scaling) | B21: =IF(B6="Direct-to-Chip (DTC)",B9*'11. Reference Data'!B78,0) | C21: IT kW × £80/kW | F21: Cost coolant distribution unit | G21: Conditional logic for CDU (capacity scaling)
A22: Manifolds & quick-connects | B22: =IF(B6="Direct-to-Chip (DTC)",B8*'11. Reference Data'!B79,0) | C22: Servers × £150/server | F22: Cost fluid distribution to racks | G22: Conditional logic for Manifolds & quick-connects
A23: Primary loop piping | B23: =IF(B6="Direct-to-Chip (DTC)",'11. Reference Data'!B80,0) | C23: Fixed per module | F23: Cost primary cooling loop | G23: Conditional logic for Primary loop piping | H23: 2. Module Capex!B24 - SUBTOTAL: DTC COOLING
A24: SUBTOTAL: DTC COOLING | B24: =SUM(B19:B23) | F24: Subtotal DTC cooling costs | G24: Sum of component values for SUBTOTAL: DTC COOLING | H24: 2. Module Capex!B60 - Applied to base infrastructure; 2. Module Capex!B63 - Base infrastructure; 6. System Capex!B15 - Cooling system
A26: IMMERSION COOLING | B26: Applies when cooling method = Immersion | F26: Section for immersion-specific equipment | G26: Section header
A27: Immersion tanks | B27: =IF(B6="Single-Phase Immersion",B7*'11. Reference Data'!B83,IF(B6="Two-Phase Immersion",B7*'11. Reference Data'!B84,0)) | C27: Racks × tank cost | F27: Cost immersion cooling vessels | G27: Conditional logic for Immersion tanks | H27: 2. Module Capex!B30 - SUBTOTAL: IMMERSION COOLING
A28: Dielectric fluid (initial fill) | B28: =IF(B6="Single-Phase Immersion",B7*'11. Reference Data'!B87*'11. Reference Data'!B85,IF(B6="Two-Phase Immersion",B7*'11. Reference Data'!B88*'11. Reference Data'!B86,0)) | C28: Racks × volume × £/litre | F28: Cost cooling fluid initial fill | G28: Conditional logic for Dielectric fluid (initial fill)
A29: Fluid management system | B29: =IF(OR(B6="Single-Phase Immersion",B6="Two-Phase Immersion"),'11. Reference Data'!B89,0) | C29: Fixed per module | F29: Cost cooling fluid initial fill | G29: Conditional logic for Fluid management system | H29: 2. Module Capex!B30 - SUBTOTAL: IMMERSION COOLING
A30: SUBTOTAL: IMMERSION COOLING | B30: =SUM(B27:B29) | F30: Subtotal immersion cooling costs | G30: Sum of component values for SUBTOTAL: IMMERSION COOLING | H30: 2. Module Capex!B60 - Applied to base infrastructure; 2. Module Capex!B63 - Base infrastructure; 6. System Capex!B15 - Cooling system
A32: POWER DISTRIBUTION
A33: Rack PDUs | B33: =B7*'11. Reference Data'!B92 | C33: Racks × £3,000/rack | F33: Cost power distribution per rack | G33: Calculated from upstream values for Rack PDUs | H33: 2. Module Capex!B36 - SUBTOTAL: POWER
A34: Module power distribution | B34: =B9*'11. Reference Data'!B93 | C34: IT kW × £180/kW | F34: Cost module-level electrical | G34: Calculated from upstream values for Module power distribution
A35: Electrical panels & switchgear | B35: ='11. Reference Data'!B94 | C35: Fixed per module | F35: Cost electrical switching equipment | G35: Pulls value from 11. Reference Data!B94 | H35: 2. Module Capex!B36 - SUBTOTAL: POWER
A36: SUBTOTAL: POWER | B36: =SUM(B33:B35) | F36: Subtotal power distribution costs | G36: Sum of component values for SUBTOTAL: POWER | H36: 2. Module Capex!B63 - Base infrastructure; 6. System Capex!B16 - Power distribution
A38: THERMAL INTEGRATION
A39: Primary heat exchanger (base) | B39: ='11. Reference Data'!B97 | C39: Fixed per module | F39: Cost thermal interface equipment | G39: Pulls value from 11. Reference Data!B97 | H39: 2. Module Capex!B43 - SUBTOTAL: THERMAL
A40: Heat exchanger (capacity scaling) | B40: =B10*'11. Reference Data'!B98 | C40: Thermal kW × £25/kW | F40: Cost thermal interface equipment | G40: Calculated from upstream values for Heat exchanger (capacity scaling)
A41: Thermal integration skid | B41: ='11. Reference Data'!B99 | C41: Fixed per module | F41: Cost heat delivery infrastructure | G41: Pulls value from 11. Reference Data!B99
A42: Instrumentation & sensors | B42: ='11. Reference Data'!B100 | C42: Fixed per module | F42: Cost monitoring equipment | G42: Pulls value from 11. Reference Data!B100 | H42: 2. Module Capex!B43 - SUBTOTAL: THERMAL
A43: SUBTOTAL: THERMAL | B43: =SUM(B39:B42) | F43: Subtotal thermal integration costs | G43: Sum of component values for SUBTOTAL: THERMAL | H43: 2. Module Capex!B63 - Base infrastructure; 6. System Capex!B17 - Thermal integration
A45: MONITORING & CONTROLS
A46: BMS base system | B46: ='11. Reference Data'!B103 | C46: Fixed per module | F46: Cost building management system | G46: Pulls value from 11. Reference Data!B103 | H46: 2. Module Capex!B49 - SUBTOTAL: MONITORING
A47: Per-rack monitoring | B47: =B7*'11. Reference Data'!B104 | C47: Racks × £500/rack | F47: Cost per-rack monitoring | G47: Calculated from upstream values for Per-rack monitoring
A48: Network infrastructure | B48: ='11. Reference Data'!B105 | C48: Fixed per module | F48: Cost network infrastructure | G48: Pulls value from 11. Reference Data!B105 | H48: 2. Module Capex!B49 - SUBTOTAL: MONITORING
A49: SUBTOTAL: MONITORING | B49: =SUM(B46:B48) | F49: Subtotal monitoring costs | G49: Sum of component values for SUBTOTAL: MONITORING | H49: 2. Module Capex!B63 - Base infrastructure; 6. System Capex!B18 - Monitoring & controls
A51: HEAT PUMP (IF ENABLED) | B51: From Module Criteria heat pump toggle | F51: Model parameter | G51: Section header
A52: Heat pump CAPEX rate (£/kWth) | B52: 600 | F52: Financial input or calculation | G52: Input parameter: Heat pump CAPEX rate (£/kWth) | H52: 2. Module Capex!B53 - Heat pump unit
A53: Heat pump unit | B53: =IF('1. Module Criteria'!B15=1,'1. Module Criteria'!B18*B52,0) | F53: Cost heat pump equipment | G53: Conditional logic for Heat pump unit | H53: 2. Module Capex!B54 - Heat pump installation; 2. Module Capex!B56 - SUBTOTAL: HEAT PUMP; 3. Module Opex!B18 - Heat pump maintenance (£/yr)
A54: Heat pump installation | B54: =IF('1. Module Criteria'!B15=1,B53*0.15,0) | F54: Cost heat pump installation | G54: Conditional logic for Heat pump installation
A55: Heat pump controls | B55: =IF('1. Module Criteria'!B15=1,15000,0) | F55: Cost heat pump control systems | G55: Conditional logic for Heat pump controls | H55: 2. Module Capex!B56 - SUBTOTAL: HEAT PUMP
A56: SUBTOTAL: HEAT PUMP | B56: =SUM(B53:B55) | F56: Subtotal heat pump costs | G56: Sum of component values for SUBTOTAL: HEAT PUMP | H56: 2. Module Capex!B65 - Heat pump; 6. System Capex!B20 - Heat pump (if enabled)
A58: COOLING METHOD PREMIUM
A59: Premium rate (%) | B59: ='0. Rack Profile'!B24/100 | C59: From Rack Profile | F59: Apply cooling technology cost premium | G59: Formula: Premium rate (%) | H59: 2. Module Capex!B60 - Applied to base infrastructure
A60: Applied to base infrastructure | B60: =(B16+B24+B30)*B59 | C60: Enclosure + Cooling × Premium % | F60: Model parameter | G60: Formula: Applied to base infrastructure | H60: 2. Module Capex!B64 - Cooling premium; 6. System Capex!B19 - Cooling method premium
A62: TOTAL MODULE CAPEX
A63: Base infrastructure | B63: =B16+B24+B30+B36+B43+B49 | F63: Model parameter | G63: Calculated from upstream values for Base infrastructure | H63: 2. Module Capex!B66 - TOTAL MODULE CAPEX; 3. Module Opex!B16 - Base maintenance (£/yr)
A64: Cooling premium | B64: =B60 | F64: Apply cooling technology cost premium | G64: Formula: Cooling premium | H64: 2. Module Capex!B66 - TOTAL MODULE CAPEX
A65: Heat pump | B65: =B56 | F65: Model parameter | G65: Formula: Heat pump | H65: 2. Module Capex!B66 - TOTAL MODULE CAPEX
A66: TOTAL MODULE CAPEX | B66: =B63+B64+B65 | F66: Sum all capital costs for investment analysis | G66: Calculated from upstream values for TOTAL MODULE CAPEX | H66: 2. Module Capex!B68 - Capex per IT kW (£/kW); 2. Module Capex!B69 - Capex per GPU (£/GPU); 3. Module Opex!B20 - Insurance (£/yr); 6. System Capex!B21 - TOTAL PER MODULE
A68: Capex per IT kW (£/kW) | B68: =B66/B9 | F68: Calculate unit cost metric for comparison | G68: Calculated from upstream values for Capex per IT kW (£/kW)
A69: Capex per GPU (£/GPU) | B69: =B66/('0. Rack Profile'!B39) | F69: Calculate unit cost metric for comparison | G69: Calculated from upstream values for Capex per GPU (£/GPU)

Sheet 3. Module Opex
A1: MODULE OPEX | F1: Intent | G1: Explanation | H1: Dependents
A2: Annual operating expenditure for a single digital boiler module | F2: Model parameter | G2: Row label only
A4: ELECTRICITY COSTS (TRIBE BEARS) | F4: Financial input or calculation
A5: Electricity rate (£/kWh) | B5: 0.18 | D5: Industrial electricity rate | F5: Set electricity cost assumption | G5: Input parameter: Electricity rate (£/kWh) | H5: 3. Module Opex!B7 - Infrastructure power cost (£/yr); 3. Module Opex!B9 - Heat pump electricity (£/yr); 7. System Opex!B34 - Electricity rate (£/kWh)
A6: Infrastructure power (from PUE) | B6: ='0. Rack Profile'!B23-1 | C6: PUE contribution - 1 | D6: Pumps, controls, BMS, lighting (~5%) | F6: Calculate cooling/support power draw | G6: Formula: Infrastructure power (from PUE) | H6: 3. Module Opex!B7 - Infrastructure power cost (£/yr)
A7: Infrastructure power cost (£/yr) | B7: ='1. Module Criteria'!B5*B6*'1. Module Criteria'!B23*B5*'1. Module Criteria'!B7 | D7: IT kW × 5% × hours × £/kWh × util | F7: Calculate cooling/support power draw | G7: Formula: Infrastructure power cost (£/yr) | H7: 3. Module Opex!B10 - SUBTOTAL: ELECTRICITY
A9: Heat pump electricity (£/yr) | B9: =IF('1. Module Criteria'!B15=1,('1. Module Criteria'!B21/'1. Module Criteria'!B17)*'1. Module Criteria'!B23*'1. Module Criteria'!B7*B5,0) | D9: (HP kWth ÷ COP) × hours × util × £/kWh | F9: Model heat pump operating expense | G9: Conditional logic for Heat pump electricity (£/yr) | H9: 3. Module Opex!B10 - SUBTOTAL: ELECTRICITY
A10: SUBTOTAL: ELECTRICITY | B10: =B7+B9 | F10: Subtotal electricity costs | G10: Calculated from upstream values for SUBTOTAL: ELECTRICITY | H10: 3. Module Opex!B29 - TOTAL MODULE OPEX (£/yr); 7. System Opex!B14 - Electricity (infra + HP)
A12: Note: Tenant rack power is pass-through (not included above) | F12: Model parameter | G12: Row label only
A14: MAINTENANCE & INSURANCE
A15: Base maintenance (% of base capex) | B15: 0.03 | F15: Model ongoing maintenance expense | G15: Input parameter: Base maintenance (% of base capex) | H15: 3. Module Opex!B16 - Base maintenance (£/yr)
A16: Base maintenance (£/yr) | B16: ='2. Module Capex'!B63*B15 | F16: Model ongoing maintenance expense | G16: Formula: Base maintenance (£/yr) | H16: 3. Module Opex!B21 - SUBTOTAL: MAINTENANCE & INSURANCE
A17: Heat pump maintenance (% of HP capex) | B17: 0.02 | F17: Model ongoing maintenance expense | G17: Input parameter: Heat pump maintenance (% of HP capex) | H17: 3. Module Opex!B18 - Heat pump maintenance (£/yr)
A18: Heat pump maintenance (£/yr) | B18: =IF('1. Module Criteria'!B15=1,'2. Module Capex'!B53*B17,0) | F18: Model ongoing maintenance expense | G18: Conditional logic for Heat pump maintenance (£/yr) | H18: 3. Module Opex!B21 - SUBTOTAL: MAINTENANCE & INSURANCE
A19: Insurance (% of total capex) | B19: 0.01 | F19: Model insurance expense | G19: Input parameter: Insurance (% of total capex) | H19: 3. Module Opex!B20 - Insurance (£/yr)
A20: Insurance (£/yr) | B20: ='2. Module Capex'!B66*B19 | F20: Model insurance expense | G20: Formula: Insurance (£/yr) | H20: 3. Module Opex!B21 - SUBTOTAL: MAINTENANCE & INSURANCE
A21: SUBTOTAL: MAINTENANCE & INSURANCE | B21: =B16+B18+B20 | F21: Subtotal maintenance and insurance | G21: Calculated from upstream values for SUBTOTAL: MAINTENANCE & INSURANCE | H21: 3. Module Opex!B29 - TOTAL MODULE OPEX (£/yr); 7. System Opex!B15 - Maintenance & insurance
A23: OTHER OPERATING COSTS
A24: Site lease/licence (£/yr) | B24: 15000 | D24: Payment to industrial host (if any) | F24: Model overhead operating expenses | G24: Input assumption: Site lease/licence (£/yr) | H24: 3. Module Opex!B27 - SUBTOTAL: OTHER
A25: Remote monitoring & NOC (£/yr) | B25: 12000 | D25: 24/7 monitoring, allocated headcount | F25: Model overhead operating expenses | G25: Input assumption: Remote monitoring & NOC (£/yr)
A26: Connectivity & admin (£/yr) | B26: 8000 | F26: Model overhead operating expenses | G26: Input assumption: Connectivity & admin (£/yr) | H26: 3. Module Opex!B27 - SUBTOTAL: OTHER
A27: SUBTOTAL: OTHER | B27: =SUM(B24:B26) | F27: Subtotal other operating costs | G27: Sum of component values for SUBTOTAL: OTHER | H27: 3. Module Opex!B29 - TOTAL MODULE OPEX (£/yr); 7. System Opex!B16 - Other (site, NOC, admin)
A29: TOTAL MODULE OPEX (£/yr) | B29: =B10+B21+B27 | F29: Sum operating costs for profitability analysis | G29: Calculated from upstream values for TOTAL MODULE OPEX (£/yr) | H29: 7. System Opex!B17 - TOTAL PER MODULE
A31: Note: Revenue and P&L calculations moved to System P&L sheet | F31: Model parameter | G31: Row label only
A32: Module-level revenue is theoretical; actual revenue depends on buyer absorption | F32: Model parameter | G32: Row label only

Sheet 4. Module Flow
A1: MODULE FLOW ANALYSIS | F1: Intent | G1: Explanation | H1: Dependents
A2: Hydraulic calculations for a single digital boiler module | F2: Model parameter | G2: Row label only
A4: CONSTANTS
A5: Specific heat of water (kJ/kg·K) | B5: 4.18 | F5: Model parameter | G5: Input parameter: Specific heat of water (kJ/kg·K) | H5: 4. Module Flow!B14 - Mass flow rate (kg/s); 4. Module Flow!B24 - Mass flow rate (kg/s)
A6: Water density (kg/L) | B6: 1 | F6: Model parameter | G6: Flag enabled for Water density (kg/L) | H6: 4. Module Flow!B15 - Volume flow rate (L/s); 4. Module Flow!B25 - Volume flow rate (L/s)
A8: SOURCE LOOP (Servers → Heat Pump) | F8: Model parameter
A9: Thermal power (kWth) | B9: ='1. Module Criteria'!B11 | D9: Heat captured from servers | F9: Pull heat load for flow calculations | G9: Pulls value from 1. Module Criteria!B11 | H9: 4. Module Flow!B14 - Mass flow rate (kg/s)
A10: Inlet temperature (°C) | B10: ='1. Module Criteria'!B12 | F10: Define temperature differential for flow sizing | G10: Pulls value from 1. Module Criteria!B12 | H10: 4. Module Flow!B12 - Outlet temperature (°C)
A11: Source loop ΔT (°C) | B11: =IF('0. Rack Profile'!B17="Direct-to-Chip (DTC)",'11. Reference Data'!E23,IF('0. Rack Profile'!B17="Single-Phase Immersion",'11. Reference Data'!E24,IF('0. Rack Profile'!B17="Two-Phase Immersion",'11. Reference Data'!E25,IF('0. Rack Profile'!B17="Rear Door Heat Exchanger",'11. Reference Data'!E26,'11. Reference Data'!E27)))) | C11: From cooling method (Reference Data) | D11: Temperature drop across HP evaporator | F11: Set temperature drop across heat source | G11: Conditional logic for Source loop ΔT (°C) | H11: 4. Module Flow!B12 - Outlet temperature (°C); 4. Module Flow!B14 - Mass flow rate (kg/s)
A12: Outlet temperature (°C) | B12: =B10-B11 | F12: Define temperature differential for flow sizing | G12: Calculated from upstream values for Outlet temperature (°C)
A14: Mass flow rate (kg/s) | B14: =B9/(B5*B11) | F14: Calculate required fluid flow rate | G14: Calculated from upstream values for Mass flow rate (kg/s) | H14: 4. Module Flow!B15 - Volume flow rate (L/s)
A15: Volume flow rate (L/s) | B15: =B14/B6 | F15: Convert to volumetric flow for pipe sizing | G15: Calculated from upstream values for Volume flow rate (L/s) | H15: 4. Module Flow!B16 - Volume flow rate (m³/hr); 4. Module Flow!B30 - Source loop pipe ID (mm)
A16: Volume flow rate (m³/hr) | B16: =B15*3.6 | F16: Convert to volumetric flow for pipe sizing | G16: Calculated from upstream values for Volume flow rate (m³/hr)
A18: SINK LOOP (Heat Pump → Industrial Partner) | F18: Model parameter
A19: Thermal power delivered (kWth) | B19: ='1. Module Criteria'!B21 | D19: With HP: includes compressor work | F19: Pull heat load for flow calculations | G19: Pulls value from 1. Module Criteria!B21 | H19: 4. Module Flow!B24 - Mass flow rate (kg/s); 4. Module Flow!B37 - Thermal capacity (kWth)
A20: Outlet temperature (°C) | B20: ='1. Module Criteria'!B22 | F20: Define temperature differential for flow sizing | G20: Pulls value from 1. Module Criteria!B22 | H20: 4. Module Flow!B22 - Return temperature (°C); 4. Module Flow!B38 - Delivery temperature (°C)
A21: Sink loop ΔT (°C) | B21: 10 | D21: HP design assumption (process ΔT used in Buyer Profile) | F21: Model parameter | G21: Input parameter: Sink loop ΔT (°C) | H21: 4. Module Flow!B22 - Return temperature (°C); 4. Module Flow!B24 - Mass flow rate (kg/s)
A22: Return temperature (°C) | B22: =B20-B21 | F22: Calculate return water temperature | G22: Calculated from upstream values for Return temperature (°C)
A24: Mass flow rate (kg/s) | B24: =B19/(B5*B21) | F24: Calculate required fluid flow rate | G24: Calculated from upstream values for Mass flow rate (kg/s) | H24: 4. Module Flow!B25 - Volume flow rate (L/s)
A25: Volume flow rate (L/s) | B25: =B24/B6 | F25: Convert to volumetric flow for pipe sizing | G25: Calculated from upstream values for Volume flow rate (L/s) | H25: 4. Module Flow!B26 - Volume flow rate (m³/hr); 4. Module Flow!B31 - Sink loop pipe ID (mm)
A26: Volume flow rate (m³/hr) | B26: =B25*3.6 | F26: Convert to volumetric flow for pipe sizing | G26: Calculated from upstream values for Volume flow rate (m³/hr) | H26: 4. Module Flow!B39 - Flow capacity (m³/hr); 5. Buyer Profile!B30 - Module flow capacity (m³/hr)
A28: PIPE SIZING GUIDANCE
A29: Design velocity (m/s) | B29: 2 | D29: Typical: 1.5-3 m/s | F29: Model parameter | G29: Input parameter: Design velocity (m/s) | H29: 4. Module Flow!B30 - Source loop pipe ID (mm); 4. Module Flow!B31 - Sink loop pipe ID (mm)
A30: Source loop pipe ID (mm) | B30: =SQRT((B15/1000)/(B29*3.14159/4))*1000 | F30: Size piping for required flow | G30: Square root calculation for Source loop pipe ID (mm) | H30: 4. Module Flow!B33 - Source loop - nearest DN
A31: Sink loop pipe ID (mm) | B31: =SQRT((B25/1000)/(B29*3.14159/4))*1000 | F31: Size piping for required flow | G31: Square root calculation for Sink loop pipe ID (mm) | H31: 4. Module Flow!B34 - Sink loop - nearest DN
A33: Source loop - nearest DN | B33: =IF(B30<28,"DN25",IF(B30<36,"DN32",IF(B30<42,"DN40",IF(B30<54,"DN50",IF(B30<68,"DN65",IF(B30<82,"DN80",IF(B30<107,"DN100","DN125+"))))))) | F33: Select standard pipe size | G33: Conditional logic for Source loop - nearest DN
A34: Sink loop - nearest DN | B34: =IF(B31<28,"DN25",IF(B31<36,"DN32",IF(B31<42,"DN40",IF(B31<54,"DN50",IF(B31<68,"DN65",IF(B31<82,"DN80",IF(B31<107,"DN100","DN125+"))))))) | F34: Select standard pipe size | G34: Conditional logic for Sink loop - nearest DN
A36: MODULE HYDRAULIC SUMMARY
A37: Thermal capacity (kWth) | B37: =B19 | F37: Summarise module heat delivery capability | G37: Formula: Thermal capacity (kWth)
A38: Delivery temperature (°C) | B38: =B20 | F38: Summarise module output temperature | G38: Formula: Delivery temperature (°C)
A39: Flow capacity (m³/hr) | B39: =B26 | F39: Summarise module flow capability | G39: Formula: Flow capacity (m³/hr)

Sheet 5. Buyer Profile
A1: BUYER PROFILE | F1: Intent | G1: Explanation | H1: Dependents
A2: Select an industrial process to see system requirements | F2: Model parameter | G2: Row label only
A4: HARDWARE CONFIGURATION
A5: Chipset | B5: ='0. Rack Profile'!B6 | F5: Pull system configuration for context | G5: Pulls value from 0. Rack Profile!B6
A6: Cooling method | B6: ='0. Rack Profile'!B17 | F6: Pull system configuration for context | G6: Pulls value from 0. Rack Profile!B17
A7: GPUs per module | B7: ='0. Rack Profile'!B39 | F7: Pull system configuration for context | G7: Pulls value from 0. Rack Profile!B39
A8: Module IT capacity (kW) | B8: ='0. Rack Profile'!B40 | F8: Pull module size for calculations | G8: Pulls value from 0. Rack Profile!B40
A10: PROCESS SELECTION
A11: Select process | B11: Pasteurisation - Medium | F11: User input to select industrial heat buyer | G11: Text value for Select process | H11: 5. Buyer Profile!B14 - Process name; 5. Buyer Profile!B15 - Size category; 5. Buyer Profile!B16 - Required temperature (°C); 5. Buyer Profile!B17 - Heat demand (kWth); 5. Buyer Profile!B18 - Operating hours/year; 5. Buyer Profile!B19 - Notes; 5. Buyer Profile!B20 - Source:; 5. Buyer Profile!B21 - Source URL:; 5. Buyer Profile!B24 - Process ΔT (°C); 6. System Capex!B10 - Selected buyer profile; ... and 3 more
A13: SELECTED PROCESS PARAMETERS
A14: Process name | B14: =IFERROR(INDEX('12. Process Library'!A:A,MATCH(B11,'12. Process Library'!G:G,0)),"-") | F14: Look up selected process details | G14: Lookup with error handling for Process name
A15: Size category | B15: =IFERROR(INDEX('12. Process Library'!B:B,MATCH(B11,'12. Process Library'!G:G,0)),"-") | F15: Identify process scale | G15: Lookup with error handling for Size category
A16: Required temperature (°C) | B16: =IFERROR(INDEX('12. Process Library'!$C$4:$C$45,MATCH(B11,'12. Process Library'!$G$4:$G$45,0)),"") | F16: Pull buyer's temperature requirement | G16: Lookup with error handling for Required temperature (°C) | H16: 5. Buyer Profile!B32 - Temperature compatible?; 5. Buyer Profile!B69 - Heat pump required?; 5. Buyer Profile!B70 - Temperature lift required (K); 8. System Flow!B14 - Required temperature (°C)
A17: Heat demand (kWth) | B17: =IFERROR(INDEX('12. Process Library'!$D$4:$D$45,MATCH(B11,'12. Process Library'!$G$4:$G$45,0)),"") | F17: Pull buyer's thermal load requirement | G17: Lookup with error handling for Heat demand (kWth) | H17: 5. Buyer Profile!B23 - Annual heat demand (MWh); 5. Buyer Profile!B25 - Required flow rate (m³/hr); 5. Buyer Profile!B33 - Modules needed (thermal); 5. Buyer Profile!B42 - Thermal utilisation (%); 5. Buyer Profile!B47 - Buyer heat absorption (kWth); 6. System Capex!B49 - Capex per kWth delivered (£/kWth); 8. System Flow!B15 - Required thermal load (kWth)
A18: Operating hours/year | B18: =IFERROR(INDEX('12. Process Library'!$E$4:$E$45,MATCH(B11,'12. Process Library'!$G$4:$G$45,0)),"") | F18: Pull buyer's usage pattern | G18: Lookup with error handling for Operating hours/year | H18: 5. Buyer Profile!B23 - Annual heat demand (MWh); 7. System Opex!B33 - Annual operating hours; 8. System Flow!B23 - Annual heat supply (MWh); 9. System P&L!B14 - Operating hours/year; 9. System P&L!B21 - Buyer operating hours/year
A19: Notes | B19: =IFERROR(INDEX('12. Process Library'!F:F,MATCH(B11,'12. Process Library'!G:G,0)),"-") | F19: Pull process context information | G19: Lookup with error handling for Notes
A20: Source: | B20: =IFERROR(INDEX('12. Process Library'!$H$4:$H$45,MATCH(B11,'12. Process Library'!$G$4:$G$45,0)),"") | F20: Reference data provenance | G20: Lookup with error handling for Source:
A21: Source URL: | B21: =IFERROR(INDEX('12. Process Library'!$J$4:$J$45,MATCH(B11,'12. Process Library'!$G$4:$G$45,0)),"") | F21: Reference data provenance | G21: Lookup with error handling for Source URL:
A23: CALCULATED DEMAND
A24: Annual heat demand (MWh) | B24: =B17*B18/1000 | F24: Pull buyer's thermal load requirement | G24: Calculated from upstream values for Annual heat demand (MWh) | H24: 8. System Flow!B17 - Annual heat demand (MWh)
A25: Process ΔT (°C) | B25: =IFERROR(INDEX('12. Process Library'!$I$4:$I$45,MATCH(B11,'12. Process Library'!$G$4:$G$45,0)),10) | C25: From Process Library (default 10 if not found) | D25: Conservative assumption for flow calculation | F25: Pull process temperature differential | G25: Lookup with error handling for Process ΔT (°C) | H25: 5. Buyer Profile!B25 - Required flow rate (m³/hr)
A26: Required flow rate (m³/hr) | B26: =B17/(4.18*B25)*3.6 | F26: Calculate buyer's flow requirement | G26: Calculated from upstream values for Required flow rate (m³/hr) | H26: 5. Buyer Profile!B34 - Modules if flow-constrained (refere...; 5. Buyer Profile!B36 - Flow deficit (m³/hr); 5. Buyer Profile!B37 - Flow ratio (buyer/system); 5. Buyer Profile!B43 - Flow utilisation (%); 5. Buyer Profile!B87 - Flow requirement met?; 8. System Flow!B16 - Required flow rate (m³/hr)
A28: SYSTEM SIZING
A29: Module thermal capacity (kWth) | B29: ='1. Module Criteria'!B21 | F29: Pull single module heat output | G29: Pulls value from 1. Module Criteria!B21 | H29: 5. Buyer Profile!B33 - Modules needed (thermal); 5. Buyer Profile!B40 - System thermal capacity (kWth)
A30: Module delivery temp (°C) | B30: ='1. Module Criteria'!B22 | F30: Pull module output temperature | G30: Pulls value from 1. Module Criteria!B22 | H30: 5. Buyer Profile!B32 - Temperature compatible?
A31: Module flow capacity (m³/hr) | B31: ='4. Module Flow'!B26 | F31: Pull single module flow capacity | G31: Pulls value from 4. Module Flow!B26 | H31: 5. Buyer Profile!B34 - Modules if flow-constrained (refere...; 5. Buyer Profile!B36 - Flow deficit (m³/hr); 5. Buyer Profile!B37 - Flow ratio (buyer/system); 5. Buyer Profile!B41 - System flow capacity (m³/hr)
A33: Temperature compatible? | B33: =IF(B30>=B16,"YES","NO - need higher temp") | F33: Check if system meets buyer temp needs | G33: Conditional logic for Temperature compatible?
A34: Modules needed (thermal) | B34: =ROUNDUP(B17/B29,0) | F34: Calculate modules for thermal demand | G34: Rounded calculation for Modules needed (thermal) | H34: 5. Buyer Profile!B35 - MODULES REQUIRED
A35: Modules if flow-constrained (reference) | B35: =ROUNDUP(B26/B31,0) | C35: Informational only - flow handled via hydraulics | F35: Calculate modules if flow-constrained | G35: Rounded calculation for Modules if flow-constrained (reference)
A36: MODULES REQUIRED | B36: =B34 | C36: Thermal sizing only - flow deficit handled separately | D36: Higher of thermal or flow requirement | F36: Determine final module count for system sizing | G36: Formula: MODULES REQUIRED | H36: 5. Buyer Profile!B36 - Flow deficit (m³/hr); 5. Buyer Profile!B37 - Flow ratio (buyer/system); 5. Buyer Profile!B40 - System thermal capacity (kWth); 5. Buyer Profile!B41 - System flow capacity (m³/hr); 5. Buyer Profile!B64 - Total modules required; 5. Buyer Profile!B65 - Total IT capacity (kW); 5. Buyer Profile!B71 - Heat pump units; 5. Buyer Profile!B72 - Total HP capacity (kWth); 5. Buyer Profile!B76 - Source loop pumps; 5. Buyer Profile!B77 - Sink loop pumps; ... and 9 more
A37: Flow deficit (m³/hr) | B37: =MAX(0,B26-B36*B31) | C37: Buyer flow need minus system flow capacity | F37: Identify shortfall requiring augmentation | G37: Bounded value for Flow deficit (m³/hr) | H37: 5. Buyer Profile!B81 - Flow augmentation pump (m³/hr); 5. Buyer Profile!B82 - Mixing valve required?; 5. Buyer Profile!B84 - Augmentation pumps required; 6. System Capex!B35 - Flow deficit (m³/hr)
A38: Flow ratio (buyer/system) | B38: =IF(B36*B31>0,B26/(B36*B31),0) | C38: >1 means hydraulic augmentation needed | F38: Compare buyer need to system capacity | G38: Conditional logic for Flow ratio (buyer/system) | H38: 5. Buyer Profile!B44 - Hydraulic augmentation needed?
A40: UTILISATION ANALYSIS | H40: 8. System Flow!B22 - System flow capacity (m³/hr)
A41: System thermal capacity (kWth) | B41: =B36*B29 | F41: Calculate total system heat output | G41: Calculated from upstream values for System thermal capacity (kWth) | H41: 5. Buyer Profile!B42 - Thermal utilisation (%); 5. Buyer Profile!B46 - System heat generation (kWth); 5. Buyer Profile!B47 - Buyer heat absorption (kWth); 5. Buyer Profile!B73 - HP electrical demand (kW); 8. System Flow!B32 - Thermal utilisation
A42: System flow capacity (m³/hr) | B42: =B36*B31 | F42: Calculate total system flow | G42: Calculated from upstream values for System flow capacity (m³/hr) | H42: 5. Buyer Profile!B43 - Flow utilisation (%); 5. Buyer Profile!B78 - Total system flow (m³/hr); 5. Buyer Profile!B79 - Header pipe size estimate (DN); 5. Buyer Profile!B86 - Augmented system flow (m³/hr); 8. System Flow!B33 - Flow utilisation
A43: Thermal utilisation (%) | B43: =B17/B41 | F43: Measure how much heat capacity is used | G43: Calculated from upstream values for Thermal utilisation (%) | H43: 8. System Flow!B34 - Binding constraint
A44: Flow utilisation (%) | B44: =IF(B88>0,B26/B88,B26/B42) | C44: Required flow / augmented system flow | F44: Measure how much flow capacity is used | G44: Conditional logic for Flow utilisation (%)
A45: Hydraulic augmentation needed? | B45: =IF(B38>1,"YES - flow ratio "&ROUND(B38,2)&"x","NO") | C45: Flow ratio > 1 means buyer needs more flow than modules provide | F45: Flag if pumps needed for flow boost | G45: Conditional logic for Hydraulic augmentation needed?
A47: HEAT BALANCE
A48: System heat generation (kWth) | B48: =B41 | C48: Total heat from modules | F48: Total heat produced by system | G48: Formula: System heat generation (kWth) | H48: 5. Buyer Profile!B48 - Excess heat (kWth); 5. Buyer Profile!B49 - Excess heat (%); 9. System P&L!B23 - Theoretical heat output (kWth)
A49: Buyer heat absorption (kWth) | B49: =MIN(B17,B41) | C49: Limited by buyer demand | F49: Actual heat buyer can use | G49: Bounded value for Buyer heat absorption (kWth) | H49: 5. Buyer Profile!B48 - Excess heat (kWth); 9. System P&L!B26 - Actual buyer absorption (kWth)
A50: Excess heat (kWth) | B50: =MAX(0,B48-B49) | C50: Requires rejection cooling | F50: Heat requiring rejection | G50: Bounded value for Excess heat (kWth) | H50: 5. Buyer Profile!B49 - Excess heat (%); 5. Buyer Profile!B50 - Heat rejection required?; 5. Buyer Profile!B51 - Rejection method; 5. Buyer Profile!B52 - Rejection capacity required (kWth); 7. System Opex!B26 - Excess heat (kWth)
A51: Excess heat (%) | B51: =IF(B48>0,B50/B48,0) | C51: Proportion of generation not sold | F51: Heat requiring rejection | G51: Conditional logic for Excess heat (%)
A52: Heat rejection required? | B52: =IF(B50>0,"YES - "&ROUND(B50,0)&" kWth rejection needed","NO - full utilisation") | F52: Size and cost rejection equipment | G52: Conditional logic for Heat rejection required?
A53: Rejection method | B53: =IF(B50=0,"-",IF(B50<'11. Reference Data'!B15,"Dry cooler",IF(B50<'11. Reference Data'!B16,"Adiabatic cooler","Cooling tower"))) | C53: Thresholds from Reference Data sheet | F53: Select appropriate rejection technology | G53: Conditional logic for Rejection method | H53: 5. Buyer Profile!B53 - Rejection capex rate (£/kWth); 5. Buyer Profile!B54 - Rejection opex rate (£/kWth/yr)
A54: Rejection capacity required (kWth) | B54: =B50 | C54: Must handle 100% of system output if buyer goes offline | F54: Size rejection equipment | G54: Formula: Rejection capacity required (kWth) | H54: 5. Buyer Profile!B55 - Rejection capex (£); 5. Buyer Profile!B56 - Annual rejection opex (£/yr); 6. System Capex!B30 - Rejection capacity required (kWth)
A55: Rejection capex rate (£/kWth) | B55: =IF(B53="-",0,IF(B53="Dry cooler",'11. Reference Data'!C10,IF(B53="Adiabatic cooler",'11. Reference Data'!C11,IF(B53="Cooling tower",'11. Reference Data'!C12,0)))) | C55: Capex rates from Reference Data sheet | F55: Cost heat rejection | G55: Conditional logic for Rejection capex rate (£/kWth) | H55: 5. Buyer Profile!B55 - Rejection capex (£); 6. System Capex!B31 - Rejection capex rate (£/kWth)
A56: Rejection opex rate (£/kWth/yr) | B56: =IF(B53="-",0,IF(B53="Dry cooler",'11. Reference Data'!D10,IF(B53="Adiabatic cooler",'11. Reference Data'!D11,IF(B53="Cooling tower",'11. Reference Data'!D12,0)))) | C56: Opex rates from Reference Data sheet | F56: Cost heat rejection | G56: Conditional logic for Rejection opex rate (£/kWth/yr) | H56: 5. Buyer Profile!B56 - Annual rejection opex (£/yr); 7. System Opex!B27 - Rejection running cost (£/kWth/yr)
A57: Rejection capex (£) | B57: =B54*B55 | C57: Capacity × capex rate (sized for worst case) | F57: Cost heat rejection | G57: Calculated from upstream values for Rejection capex (£)
A58: Annual rejection opex (£/yr) | B58: =B54*B56 | C58: ACTUAL excess heat × opex rate (normal operation) | F58: Cost heat rejection | G58: Calculated from upstream values for Annual rejection opex (£/yr)
A62: HARDWARE DEPENDENCIES
A63: Equipment requirements implied by buyer selection | F63: Model parameter | G63: Row label only
A65: Module Configuration | F65: Model parameter | G65: Row label only
A66: Total modules required | B66: =B36 | F66: Determine final module count | G66: Formula: Total modules required
A67: Total IT capacity (kW) | B67: =B36*'1. Module Criteria'!B5 | F67: Summarise compute capacity | G67: Calculated from upstream values for Total IT capacity (kW) | H67: 5. Buyer Profile!B66 - Total rack units (42U racks @ 10kW); 5. Buyer Profile!B91 - IT load (kW); 5. Buyer Profile!B92 - Cooling infrastructure (kW)
A68: Total rack units (42U racks @ 10kW) | B68: =ROUNDUP(B67/10,0) | C68: Based on IT capacity (10kW per 42U rack) | F68: Sum components for analysis | G68: Rounded calculation for Total rack units (42U racks @ 10kW) | H68: 5. Buyer Profile!B107 - 42U server racks
A70: Heat Pump Requirements | F70: Size circulation equipment | G70: Row label only
A71: Heat pump required? | B71: =IF(B16>'1. Module Criteria'!B12,"YES","NO - direct heat sufficient") | F71: Check if HP needed for buyer | G71: Conditional logic for Heat pump required?
A72: Temperature lift required (K) | B72: =IF(B16>'1. Module Criteria'!B12,B16-'1. Module Criteria'!B12,0) | F72: Calculate required HP boost | G72: Conditional logic for Temperature lift required (K)
A73: Heat pump units | B73: =B36 | C73: 1 HP per module | F73: Count HP equipment needed | G73: Formula: Heat pump units | H73: 5. Buyer Profile!B106 - Heat pump units
A74: Total HP capacity (kWth) | B74: =B36*'1. Module Criteria'!B18 | F74: Size total HP thermal capacity | G74: Calculated from upstream values for Total HP capacity (kWth)
A75: HP electrical demand (kW) | B75: =IF(OR(NOT(ISNUMBER('1. Module Criteria'!B17)),'1. Module Criteria'!B17<=1),0,B41/'1. Module Criteria'!B17) | C75: HP output / COP | F75: Calculate HP power consumption | G75: Conditional logic for HP electrical demand (kW) | H75: 5. Buyer Profile!B93 - Heat pump load (kW)
A77: Hydraulic Infrastructure | F77: Model parameter | G77: Row label only
A78: Source loop pumps | B78: =B36 | C78: 1 per module | F78: Reference data provenance | G78: Formula: Source loop pumps | H78: 5. Buyer Profile!B108 - Source circulation pumps
A79: Sink loop pumps | B79: =B36 | C79: 1 per module | F79: Size circulation equipment | G79: Formula: Sink loop pumps | H79: 5. Buyer Profile!B109 - Sink circulation pumps
A80: Total system flow (m³/hr) | B80: =B42 | F80: Sum components for analysis | G80: Formula: Total system flow (m³/hr)
A81: Header pipe size estimate (DN) | B81: =IF(B42<10,"DN50",IF(B42<25,"DN65",IF(B42<50,"DN80",IF(B42<100,"DN100","DN125+")))) | C81: Based on 2 m/s design velocity | F81: Size main distribution piping | G81: Conditional logic for Header pipe size estimate (DN)
A82: Buffer tank recommended? | B82: =IF(B36>2,"YES - system balancing","OPTIONAL") | F82: Flag if thermal buffer needed | G82: Conditional logic for Buffer tank recommended? | H82: 5. Buyer Profile!B111 - Buffer tank
A83: Flow augmentation pump (m³/hr) | B83: =B37 | C83: Sized for flow deficit | F83: Size circulation equipment | G83: Formula: Flow augmentation pump (m³/hr)
A84: Mixing valve required? | B84: =IF(B37>0,"YES","NO") | C84: Blends supply with return for higher flow | F84: Flag if temperature control needed | G84: Conditional logic for Mixing valve required?
A85: Augmentation pump power (kW) | B85: =B87*'11. Reference Data'!B121 | C85: Actual pump capacity × kW/m³/hr | F85: Size circulation equipment | G85: Calculated from upstream values for Augmentation pump power (kW) | H85: 7. System Opex!B32 - Augmentation pump power (kW)
A86: Augmentation pumps required | B86: =IF(B37>0,ROUNDUP(B37/'11. Reference Data'!B124,0),0) | C86: Rounded up to whole pumps | F86: Size circulation equipment | G86: Conditional logic for Augmentation pumps required | H86: 5. Buyer Profile!B85 - Augmentation pump capacity (m³/hr); 5. Buyer Profile!B113 - Flow augmentation pumps; 5. Buyer Profile!B114 - Mixing valves; 6. System Capex!B36 - Augmentation pumps required
A87: Augmentation pump capacity (m³/hr) | B87: =B86*'11. Reference Data'!B124 | C87: Pumps × standard capacity | F87: Size circulation equipment | G87: Calculated from upstream values for Augmentation pump capacity (m³/hr) | H87: 5. Buyer Profile!B83 - Augmentation pump power (kW); 5. Buyer Profile!B86 - Augmented system flow (m³/hr); 7. System Opex!B31 - Augmentation pump capacity (m³/hr)
A88: Augmented system flow (m³/hr) | B88: =B42+B87 | C88: Base module flow + augmentation | F88: Fluid flow parameter for hydraulic design | G88: Calculated from upstream values for Augmented system flow (m³/hr) | H88: 5. Buyer Profile!B43 - Flow utilisation (%); 5. Buyer Profile!B87 - Flow requirement met?
A89: Flow requirement met? | B89: =IF(B88>=B26,"YES","NO - shortfall of "&ROUND(B26-B88,1)&" m³/hr") | C89: Augmented flow >= required flow | F89: Fluid flow parameter for hydraulic design | G89: Conditional logic for Flow requirement met?
A92: Electrical Infrastructure | F92: Model parameter | G92: Row label only
A93: IT load (kW) | B93: =B67 | F93: Calculate IT electrical demand | G93: Formula: IT load (kW) | H93: 5. Buyer Profile!B94 - Total electrical demand (kW)
A94: Cooling infrastructure (kW) | B94: =B67*'1. Module Criteria'!B7*0.05 | C94: 5% of IT load for pumps/controls | F94: Calculate cooling electrical demand | G94: Calculated from upstream values for Cooling infrastructure (kW) | H94: 5. Buyer Profile!B94 - Total electrical demand (kW)
A95: Heat pump load (kW) | B95: =B75 | F95: Size circulation equipment | G95: Formula: Heat pump load (kW) | H95: 5. Buyer Profile!B94 - Total electrical demand (kW)
A96: Total electrical demand (kW) | B96: =B93+B94+B95 | F96: Sum all electrical loads | G96: Calculated from upstream values for Total electrical demand (kW) | H96: 5. Buyer Profile!B95 - Grid connection (kVA @ 0.9 PF)
A97: Grid connection (kVA @ 0.9 PF) | B97: =ROUNDUP(B96/0.9,-1) | C97: Rounded to nearest 10 kVA | F97: Size grid supply requirement | G97: Rounded calculation for Grid connection (kVA @ 0.9 PF)
A99: Space Requirements | F99: Model parameter
A100: Module footprint each (m²) | B100: 15 | C100: Typical 20ft container | F100: Calculate space requirements | G100: Input parameter: Module footprint each (m²) | H100: 5. Buyer Profile!B99 - Total module footprint (m²)
A101: Total module footprint (m²) | B101: =B36*B100 | F101: Calculate space requirements | G101: Calculated from upstream values for Total module footprint (m²) | H101: 5. Buyer Profile!B101 - Total site area (m²)
A102: Plant room allowance (m²) | B102: =IF(B36>2,25,15) | C102: For headers, buffer, controls | F102: Allocate support equipment space | G102: Conditional logic for Plant room allowance (m²) | H102: 5. Buyer Profile!B101 - Total site area (m²)
A103: Total site area (m²) | B103: =B101+B102 | C103: Excluding access/clearances | F103: Calculate space requirements | G103: Calculated from upstream values for Total site area (m²)
A105: BILL OF MATERIALS SUMMARY
A106: Item | B106: Qty | C106: Notes | F106: Model parameter | G106: Text value for Item
A107: Modular DC units (250kW IT) | B107: =B36 | C107: Containerised data centre | F107: Generate equipment list for procurement | G107: Formula: Modular DC units (250kW IT)
A108: Heat pump units | B108: =B73 | C108: Industrial HTHP, CO2 or NH3 | F108: Count HP equipment needed | G108: Formula: Heat pump units
A109: 42U server racks | B109: =B68 | C109: @ 10kW per rack | F109: Generate equipment list for procurement | G109: Formula: 42U server racks
A110: Source circulation pumps | B110: =B78 | C110: Grundfos/Wilo industrial | F110: Reference data provenance | G110: Formula: Source circulation pumps
A111: Sink circulation pumps | B111: =B79 | C111: Variable speed | F111: Size circulation equipment | G111: Formula: Sink circulation pumps
A112: Plate heat exchangers | B112: =B36 | C112: Alfa Laval or equiv | F112: Model parameter | G112: Formula: Plate heat exchangers
A113: Buffer tank | B113: =IF(B82="YES - system balancing",1,0) | C113: If multi-module | F113: Flag if thermal buffer needed | G113: Conditional logic for Buffer tank
A114: BMS/Controls package | B114: 1 | C114: Central monitoring | F114: Model parameter | G114: Flag enabled for BMS/Controls package
A115: Flow augmentation pumps | B115: =B86 | C115: For flow deficit (if any) | F115: Size circulation equipment | G115: Formula: Flow augmentation pumps
A116: Mixing valves | B116: =IF(B86>0,1,0) | C116: 1 if augmentation needed | F116: Flag if temperature control needed | G116: Conditional logic for Mixing valves

Sheet 6. System Capex
A1: SYSTEM CAPEX | F1: Intent | G1: Explanation | H1: Dependents
A2: Capital expenditure for complete system serving selected buyer | F2: Model parameter | G2: Row label only
A4: HARDWARE CONFIGURATION
A5: Chipset | B5: ='0. Rack Profile'!B6 | F5: Model parameter | G5: Pulls value from 0. Rack Profile!B6
A6: Cooling method | B6: ='0. Rack Profile'!B17 | F6: Model parameter | G6: Pulls value from 0. Rack Profile!B17
A7: GPUs per module | B7: ='0. Rack Profile'!B39 | F7: Model parameter | G7: Pulls value from 0. Rack Profile!B39
A9: SYSTEM CONFIGURATION
A10: Selected buyer profile | B10: ='5. Buyer Profile'!B11 | F10: Model parameter | G10: Pulls value from 5. Buyer Profile!B11
A11: Modules required | B11: ='5. Buyer Profile'!B36 | F11: Pull module count from buyer sizing | G11: Pulls value from 5. Buyer Profile!B35 | H11: 6. System Capex!B24 - Total module capex; 6. System Capex!B27 - Integration & commissioning; 6. System Capex!B48 - Capex per IT kW (£/kW)
A13: MODULE CAPEX (per unit) | F13: Model parameter
A14: Enclosure & structure | B14: ='2. Module Capex'!B16 | F14: Pull per-module enclosure cost | G14: Pulls value from 2. Module Capex!B16
A15: Cooling system | B15: ='2. Module Capex'!B24+'2. Module Capex'!B30 | C15: DTC or Immersion (whichever applies) | F15: Pull per-module cooling cost | G15: Formula: Cooling system
A16: Power distribution | B16: ='2. Module Capex'!B36 | F16: Pull per-module power cost | G16: Pulls value from 2. Module Capex!B36
A17: Thermal integration | B17: ='2. Module Capex'!B43 | F17: Pull per-module thermal cost | G17: Pulls value from 2. Module Capex!B43
A18: Monitoring & controls | B18: ='2. Module Capex'!B49 | F18: Pull per-module monitoring cost | G18: Pulls value from 2. Module Capex!B49
A19: Cooling method premium | B19: ='2. Module Capex'!B60 | C19: From Rack Profile | F19: Pull cooling technology premium | G19: Pulls value from 2. Module Capex!B60
A20: Heat pump (if enabled) | B20: ='2. Module Capex'!B56 | F20: Pull per-module HP cost | G20: Pulls value from 2. Module Capex!B56
A21: TOTAL PER MODULE | B21: ='2. Module Capex'!B66 | F21: Sum per-module costs for scaling | G21: Pulls value from 2. Module Capex!B66 | H21: 6. System Capex!B24 - Total module capex
A24: Total module capex | B24: =B21*B11 | F24: Calculate all modules cost | G24: Calculated from upstream values for Total module capex | H24: 6. System Capex!B26 - Shared infrastructure (£); 6. System Capex!B43 - Base system capex (excl. rejection)
A25: Shared infrastructure (%) | B25: 0.05 | C25: Common civils, shared services (scales with modules) | F25: Add common infrastructure cost | G25: Input parameter: Shared infrastructure (%) | H25: 6. System Capex!B26 - Shared infrastructure (£)
A26: Shared infrastructure (£) | B26: =B24*B25 | F26: Add common infrastructure cost | G26: Calculated from upstream values for Shared infrastructure (£) | H26: 6. System Capex!B43 - Base system capex (excl. rejection)
A27: Integration & commissioning | B27: =IF(B11>1,25000*(B11-1),0) | C27: £25k per additional module | F27: Add system integration cost | G27: Conditional logic for Integration & commissioning | H27: 6. System Capex!B43 - Base system capex (excl. rejection)
C29: Additional capex for cooling
A30: Rejection capacity required (kWth) | B30: ='5. Buyer Profile'!B54 | F30: Add heat rejection equipment cost | G30: Pulls value from 5. Buyer Profile!B52 | H30: 6. System Capex!B32 - Heat rejection capex
A31: Rejection capex rate (£/kWth) | B31: ='5. Buyer Profile'!B55 | F31: Add heat rejection equipment cost | G31: Pulls value from 5. Buyer Profile!B53 | H31: 6. System Capex!B32 - Heat rejection capex
A32: Heat rejection capex | B32: =IF(B30>0,B30*B31,0) | C32: Sized for 100% rejection (buyer offline scenario) | F32: Add heat rejection equipment cost | G32: Conditional logic for Heat rejection capex | H32: 6. System Capex!B44 - Heat rejection capex
A34: HYDRAULIC AUGMENTATION
A35: Flow deficit (m³/hr) | B35: ='5. Buyer Profile'!B37 | F35: Fluid flow parameter for hydraulic design | G35: Pulls value from 5. Buyer Profile!B36 | H35: 6. System Capex!B38 - Mixing valve + controls; 6. System Capex!B39 - Pipe upsizing allowance
A36: Augmentation pumps required | B36: ='5. Buyer Profile'!B86 | F36: Add flow augmentation cost | G36: Pulls value from 5. Buyer Profile!B84 | H36: 6. System Capex!B37 - Augmentation pump capex
A37: Augmentation pump capex | B37: =B36*'11. Reference Data'!B124*'11. Reference Data'!B120 | C37: Pumps × capacity × £/m³/hr | F37: Add flow augmentation cost | G37: Calculated from upstream values for Augmentation pump capex | H37: 6. System Capex!B40 - SUBTOTAL: HYDRAULIC AUGMENTATION
A38: Mixing valve + controls | B38: =IF(B35>0,'11. Reference Data'!B122,0) | F38: Model parameter | G38: Conditional logic for Mixing valve + controls
A39: Pipe upsizing allowance | B39: =IF(B35>20,B35*'11. Reference Data'!B123,0) | C39: If flow deficit > 20 m³/hr | F39: Model parameter | G39: Conditional logic for Pipe upsizing allowance | H39: 6. System Capex!B40 - SUBTOTAL: HYDRAULIC AUGMENTATION
A40: SUBTOTAL: HYDRAULIC AUGMENTATION | B40: =SUM(B37:B39) | F40: Subtotal flow augmentation costs | G40: Sum of component values for SUBTOTAL: HYDRAULIC AUGMENTATION | H40: 6. System Capex!B45 - Hydraulic augmentation capex
A42: TOTAL SYSTEM CAPEX
A43: Base system capex (excl. rejection) | B43: =B24+B26+B27 | C43: Module + shared + integration costs | F43: Add heat rejection equipment cost | G43: Calculated from upstream values for Base system capex (excl. rejection) | H43: 6. System Capex!B46 - TOTAL SYSTEM CAPEX
A44: Heat rejection capex | B44: =B32 | F44: Add heat rejection equipment cost | G44: Formula: Heat rejection capex | H44: 6. System Capex!B46 - TOTAL SYSTEM CAPEX
A45: Hydraulic augmentation capex | B45: =B40 | F45: Add flow augmentation cost | G45: Formula: Hydraulic augmentation capex | H45: 6. System Capex!B46 - TOTAL SYSTEM CAPEX
A46: TOTAL SYSTEM CAPEX | B46: =B43+B44+B45 | F46: Sum complete investment requirement | G46: Calculated from upstream values for TOTAL SYSTEM CAPEX | H46: 6. System Capex!B48 - Capex per IT kW (£/kW); 6. System Capex!B49 - Capex per kWth delivered (£/kWth); 9. System P&L!B48 - Total system capex (£)
A48: Capex per IT kW (£/kW) | B48: =B46/(B11*'0. Rack Profile'!B40) | F48: Calculate unit cost metric | G48: Calculated from upstream values for Capex per IT kW (£/kW)
A49: Capex per kWth delivered (£/kWth) | B49: =B46/'5. Buyer Profile'!B17 | F49: Calculate unit cost metric | G49: Calculated from upstream values for Capex per kWth delivered (£/kWth)

Sheet 7. System Opex
A1: SYSTEM OPEX | F1: Intent | G1: Explanation | H1: Dependents
A2: Annual operating costs and revenue for complete system | F2: Financial input or calculation | G2: Row label only
A4: HARDWARE CONFIGURATION
A5: Chipset | B5: ='0. Rack Profile'!B6 | F5: Model parameter | G5: Pulls value from 0. Rack Profile!B6
A6: Cooling method | B6: ='0. Rack Profile'!B17 | F6: Model parameter | G6: Pulls value from 0. Rack Profile!B17
A7: GPUs per module | B7: ='0. Rack Profile'!B39 | F7: Model parameter | G7: Pulls value from 0. Rack Profile!B39
A9: SYSTEM CONFIGURATION
A10: Selected buyer profile | B10: ='5. Buyer Profile'!B11 | F10: Model parameter | G10: Pulls value from 5. Buyer Profile!B11
A11: Modules in system | B11: ='5. Buyer Profile'!B36 | F11: Pull module count | G11: Pulls value from 5. Buyer Profile!B35 | H11: 7. System Opex!B20 - Total module opex
A13: MODULE OPEX (per unit, £/yr) | F13: Financial input or calculation
A14: Electricity (infra + HP) | B14: ='3. Module Opex'!B10 | F14: Pull per-module electricity cost | G14: Pulls value from 3. Module Opex!B10
A15: Maintenance & insurance | B15: ='3. Module Opex'!B21 | F15: Pull per-module maintenance cost | G15: Pulls value from 3. Module Opex!B21
A16: Other (site, NOC, admin) | B16: ='3. Module Opex'!B27 | F16: Pull per-module overhead cost | G16: Pulls value from 3. Module Opex!B27
A17: TOTAL PER MODULE | B17: ='3. Module Opex'!B29 | F17: Sum per-module opex for scaling | G17: Pulls value from 3. Module Opex!B29 | H17: 7. System Opex!B20 - Total module opex
A19: SYSTEM OPEX (all modules, £/yr) | F19: Pull module count
A20: Total module opex | B20: =B17*B11 | F20: Calculate all modules opex | G20: Calculated from upstream values for Total module opex | H20: 7. System Opex!B22 - Shared overhead (£/yr); 7. System Opex!B23 - Base system opex (excl. rejection)
A21: Shared overhead (%) | B21: 0.05 | D21: Central management allocation | F21: Add common operating costs | G21: Input parameter: Shared overhead (%) | H21: 7. System Opex!B22 - Shared overhead (£/yr)
A22: Shared overhead (£/yr) | B22: =B20*B21 | F22: Add common operating costs | G22: Calculated from upstream values for Shared overhead (£/yr) | H22: 7. System Opex!B23 - Base system opex (excl. rejection)
A23: Base system opex (excl. rejection) | B23: =B20+B22 | C23: Module + shared overhead costs | F23: Sum base operating costs | G23: Calculated from upstream values for Base system opex (excl. rejection) | H23: 7. System Opex!B29 - Heat rejection uplift (%); 7. System Opex!B37 - TOTAL SYSTEM OPEX; 9. System P&L!B39 - Base system opex (£/yr)
A25: HEAT REJECTION OPEX
A26: Excess heat (kWth) | B26: ='5. Buyer Profile'!B50 | C26: Actual excess heat in normal operation | F26: Pull heat requiring rejection | G26: Pulls value from 5. Buyer Profile!B48 | H26: 7. System Opex!B28 - Heat rejection opex (£/yr)
A27: Rejection running cost (£/kWth/yr) | B27: ='5. Buyer Profile'!B56 | C27: Variable rate from Buyer Profile based on rejection method | F27: Add heat rejection operating cost | G27: Pulls value from 5. Buyer Profile!B54 | H27: 7. System Opex!B28 - Heat rejection opex (£/yr)
A28: Heat rejection opex (£/yr) | B28: =IF(B26>0,B26*B27,0) | F28: Add heat rejection operating cost | G28: Conditional logic for Heat rejection opex (£/yr) | H28: 7. System Opex!B29 - Heat rejection uplift (%); 7. System Opex!B37 - TOTAL SYSTEM OPEX; 9. System P&L!B40 - Heat rejection opex (£/yr)
A29: Heat rejection uplift (%) | B29: =IF(B23>0,B28/B23,0) | C29: Additional opex for cooling | F29: Add heat rejection operating cost | G29: Conditional logic for Heat rejection uplift (%)
A30: HYDRAULIC AUGMENTATION OPEX
A31: Augmentation pump capacity (m³/hr) | B31: ='5. Buyer Profile'!B87 | F31: Add pump operating cost | G31: Pulls value from 5. Buyer Profile!B85
A32: Augmentation pump power (kW) | B32: ='5. Buyer Profile'!B85 | F32: Add pump operating cost | G32: Pulls value from 5. Buyer Profile!B83 | H32: 7. System Opex!B35 - Augmentation pump electricity (£/yr...
A33: Annual operating hours | B33: ='5. Buyer Profile'!B18 | C33: From buyer operating profile | F33: Model parameter | G33: Pulls value from 5. Buyer Profile!B18 | H33: 7. System Opex!B35 - Augmentation pump electricity (£/yr...
A34: Electricity rate (£/kWh) | B34: ='3. Module Opex'!B5 | F34: Financial input or calculation | G34: Pulls value from 3. Module Opex!B5 | H34: 7. System Opex!B35 - Augmentation pump electricity (£/yr...
A35: Augmentation pump electricity (£/yr) | B35: =B32*B33*B34 | F35: Add pump operating cost | G35: Calculated from upstream values for Augmentation pump electricity (£/yr) | H35: 7. System Opex!B37 - TOTAL SYSTEM OPEX; 9. System P&L!B41 - Hydraulic augmentation opex (£/yr)
A37: TOTAL SYSTEM OPEX | B37: =B23+B28+B35 | F37: Sum complete operating costs | G37: Calculated from upstream values for TOTAL SYSTEM OPEX | H37: 9. System P&L!B42 - TOTAL OPEX (£/yr)
A39: Note: Revenue and P&L calculations moved to System P&L sheet | F39: Model parameter | G39: Row label only
A40: See "9. System P&L" for actual revenue based on buyer heat absorption | F40: Model parameter | G40: Row label only

Sheet 8. System Flow
A1: SYSTEM FLOW ANALYSIS | F1: Intent | G1: Explanation | H1: Dependents
A2: Hydraulic analysis for complete system serving selected buyer | F2: Model parameter | G2: Row label only
A4: HARDWARE CONFIGURATION
A5: Chipset | B5: ='0. Rack Profile'!B6 | F5: Model parameter | G5: Pulls value from 0. Rack Profile!B6
A6: Cooling method | B6: ='0. Rack Profile'!B17 | F6: Model parameter | G6: Pulls value from 0. Rack Profile!B17
A7: Capture temperature (°C) | B7: ='0. Rack Profile'!B21 | F7: Pull heat source temperature | G7: Pulls value from 0. Rack Profile!B21
A9: SYSTEM CONFIGURATION
A10: Selected buyer profile | B10: ='5. Buyer Profile'!B11 | F10: Pull sizing from buyer analysis | G10: Pulls value from 5. Buyer Profile!B11
A11: Modules in system | B11: ='5. Buyer Profile'!B36 | F11: Pull sizing from buyer analysis | G11: Pulls value from 5. Buyer Profile!B35
A13: BUYER REQUIREMENTS
A14: Required temperature (°C) | B14: ='5. Buyer Profile'!B16 | F14: Pull buyer temperature requirement | G14: Pulls value from 5. Buyer Profile!B16 | H14: 8. System Flow!B26 - Temperature (°C)
A15: Required thermal load (kWth) | B15: ='5. Buyer Profile'!B17 | F15: Pull buyer heat requirement | G15: Pulls value from 5. Buyer Profile!B17 | H15: 8. System Flow!B27 - Thermal load (kWth); 8. System Flow!B36 - Spare capacity (kWth)
A16: Required flow rate (m³/hr) | B16: ='5. Buyer Profile'!B26 | F16: Pull buyer flow requirement | G16: Pulls value from 5. Buyer Profile!B25 | H16: 8. System Flow!B28 - Flow rate (m³/hr); 8. System Flow!B37 - Spare capacity (m³/hr); 8. System Flow!B41 - Main header pipe ID (mm)
A17: Annual heat demand (MWh) | B17: ='5. Buyer Profile'!B24 | F17: Pull buyer annual energy need | G17: Pulls value from 5. Buyer Profile!B23 | H17: 8. System Flow!B29 - Annual energy (MWh)
A19: SYSTEM CAPACITY
A20: Delivery temperature (°C) | B20: ='1. Module Criteria'!B22 | F20: Pull system output temperature | G20: Pulls value from 1. Module Criteria!B22 | H20: 8. System Flow!C26 - Temperature (°C)
A21: System thermal capacity (kWth) | B21: ='5. Buyer Profile'!B41 | F21: Pull system heat capacity | G21: Pulls value from 5. Buyer Profile!B38 | H21: 8. System Flow!B23 - Annual heat supply (MWh); 8. System Flow!C27 - Thermal load (kWth); 8. System Flow!B36 - Spare capacity (kWth)
A22: System flow capacity (m³/hr) | B22: ='5. Buyer Profile'!B42 | F22: Pull system flow capacity | G22: Pulls value from 5. Buyer Profile!B39 | H22: 8. System Flow!C28 - Flow rate (m³/hr); 8. System Flow!B37 - Spare capacity (m³/hr)
A23: Annual heat supply (MWh) | B23: =B21*'5. Buyer Profile'!B18/1000 | C23: kWth × buyer hours ÷ 1000 | F23: Calculate annual heat available | G23: Calculated from upstream values for Annual heat supply (MWh) | H23: 8. System Flow!C29 - Annual energy (MWh)
A25: SUPPLY vs DEMAND MATCH | B25: Required | C25: Supplied | D25: Match? | F25: Compare system capability to buyer need | G25: Text value for SUPPLY vs DEMAND MATCH
A26: Temperature (°C) | B26: =B14 | C26: =B20 | D26: =IF(C26>=B26,"✓ YES","✗ NO - need "&B26&"°C") | F26: Temperature parameter for thermal design | G26: Formula: Temperature (°C) | H26: 8. System Flow!D26 - Temperature (°C)
A27: Thermal load (kWth) | B27: =B15 | C27: =B21 | D27: =IF(C27>=B27,"✓ YES - "&ROUND((C27-B27),0)&" kWth spare","✗ SHORT "&ROUND((B27-C27),0)&" kWth") | F27: Power or thermal capacity metric | G27: Formula: Thermal load (kWth) | H27: 8. System Flow!D27 - Thermal load (kWth)
A28: Flow rate (m³/hr) | B28: =B16 | C28: =B22 | D28: =IF(C28>=B28,"✓ YES - "&ROUND((C28-B28),1)&" m³/hr spare","✗ SHORT "&ROUND((B28-C28),1)&" m³/hr") | F28: Efficiency or utilisation metric | G28: Formula: Flow rate (m³/hr) | H28: 8. System Flow!D28 - Flow rate (m³/hr)
A29: Annual energy (MWh) | B29: =B17 | C29: =B23 | D29: =IF(C29>=B29,"✓ YES - "&ROUND((C29-B29),0)&" MWh spare","✗ SHORT "&ROUND((B29-C29),0)&" MWh") | F29: Model parameter | G29: Formula: Annual energy (MWh) | H29: 8. System Flow!D29 - Annual energy (MWh)
A31: UTILISATION SUMMARY
A32: Thermal utilisation | B32: ='5. Buyer Profile'!B43 | F32: Show capacity usage metrics | G32: Pulls value from 5. Buyer Profile!B40
A33: Flow utilisation | B33: ='5. Buyer Profile'!B44 | F33: Show capacity usage metrics | G33: Pulls value from 5. Buyer Profile!B41
A34: Binding constraint | B34: =IF(AND(ISNUMBER('5. Buyer Profile'!B43),ISNUMBER('5. Buyer Profile'!B44)),IF('5. Buyer Profile'!B43>='5. Buyer Profile'!B44,"Thermal","Flow"),"-") | F34: Identify limiting factor | G34: Pulls value from 5. Buyer Profile!B42
A36: Spare capacity (kWth) | B36: =B21-B15 | F36: Show available headroom | G36: Calculated from upstream values for Spare capacity (kWth)
A37: Spare capacity (m³/hr) | B37: =B22-B16 | F37: Show available headroom | G37: Calculated from upstream values for Spare capacity (m³/hr)
A39: SYSTEM PIPE SIZING
A40: Design velocity (m/s) | B40: 2 | F40: Model parameter | G40: Input parameter: Design velocity (m/s) | H40: 8. System Flow!B41 - Main header pipe ID (mm)
A41: Main header pipe ID (mm) | B41: =SQRT((B16/3600)/(B40*3.14159/4))*1000 | F41: Size main distribution piping | G41: Square root calculation for Main header pipe ID (mm) | H41: 8. System Flow!B42 - Nearest DN size
A42: Nearest DN size | B42: =IF(B41<28,"DN25",IF(B41<36,"DN32",IF(B41<42,"DN40",IF(B41<54,"DN50",IF(B41<68,"DN65",IF(B41<82,"DN80",IF(B41<107,"DN100",IF(B41<131,"DN125",IF(B41<159,"DN150","DN200+"))))))))) | F42: Select standard pipe size | G42: Conditional logic for Nearest DN size

Sheet 9. System P&L
A1: SYSTEM P&L | F1: Intent | G1: Explanation | H1: Dependents
A2: Profit & Loss analysis for complete system serving selected buyer | F2: Model parameter | G2: Row label only
A3: NOTE: Heat revenue reflects ACTUAL buyer absorption, not theoretical module output | F3: Pull actual heat buyer takes | G3: Row label only
A5: CONFIGURATION
A6: Selected buyer profile | B6: ='5. Buyer Profile'!B11 | F6: Pull selected buyer scenario | G6: Pulls value from 5. Buyer Profile!B11
A7: Modules in system | B7: ='5. Buyer Profile'!B36 | F7: Pull system size | G7: Pulls value from 5. Buyer Profile!B35 | H7: 9. System P&L!B17 - TOTAL COMPUTE REVENUE (£/yr)
A8: Chipset | B8: ='0. Rack Profile'!B6 | F8: Pull configuration for context | G8: Pulls value from 0. Rack Profile!B6
A9: Cooling method | B9: ='0. Rack Profile'!B17 | F9: Pull configuration for context | G9: Pulls value from 0. Rack Profile!B17
A11: COMPUTE REVENUE
A12: Module IT capacity (kW) | B12: ='1. Module Criteria'!B5 | C12: From Module Criteria | F12: Pull module size for revenue calc | G12: Pulls value from 1. Module Criteria!B5 | H12: 9. System P&L!B16 - Compute revenue per module (£/yr)
A13: Rack rate (£/kW/month) | B13: ='1. Module Criteria'!B6 | C13: Input assumption - pulled from Module Criteria | F13: Pull compute pricing assumption | G13: Pulls value from 1. Module Criteria!B6 | H13: 9. System P&L!B16 - Compute revenue per module (£/yr)
A14: Operating hours/year | B14: ='5. Buyer Profile'!B18 | C14: From selected process profile | F14: Pull utilisation for revenue calc | G14: Pulls value from 5. Buyer Profile!B18
A15: Utilisation assumption (%) | B15: ='1. Module Criteria'!B7 | C15: Input assumption - pulled from Module Criteria | F15: Pull capacity utilisation rate | G15: Pulls value from 1. Module Criteria!B7 | H15: 9. System P&L!B16 - Compute revenue per module (£/yr)
A16: Compute revenue per module (£/yr) | B16: =B12*B13*12*B15 | C16: Racks × rate × 12 months × utilisation | F16: Calculate single module compute income | G16: Calculated from upstream values for Compute revenue per module (£/yr) | H16: 9. System P&L!B17 - TOTAL COMPUTE REVENUE (£/yr)
A17: TOTAL COMPUTE REVENUE (£/yr) | B17: =B16*B7 | C17: Per module × number of modules | F17: Calculate all modules compute income | G17: Calculated from upstream values for TOTAL COMPUTE REVENUE (£/yr) | H17: 9. System P&L!B33 - Compute revenue (£/yr)
A19: HEAT REVENUE
A20: Heat price (£/MWh) | B20: ='1. Module Criteria'!B29 | C20: Input assumption - pulled from Module Criteria | F20: Pull heat sales pricing | G20: Pulls value from 1. Module Criteria!B29 | H20: 9. System P&L!B24 - Theoretical heat revenue (£/yr); 9. System P&L!B27 - ACTUAL HEAT REVENUE (£/yr)
A21: Buyer operating hours/year | B21: ='5. Buyer Profile'!B18 | C21: Hours buyer process runs annually | F21: Pull utilisation for revenue calc | G21: Pulls value from 5. Buyer Profile!B18 | H21: 9. System P&L!B24 - Theoretical heat revenue (£/yr); 9. System P&L!B27 - ACTUAL HEAT REVENUE (£/yr)
A23: Theoretical heat output (kWth) | B23: ='5. Buyer Profile'!B48 | C23: Total system thermal generation capacity | F23: Calculate max heat sales potential | G23: Pulls value from 5. Buyer Profile!B46 | H23: 9. System P&L!B24 - Theoretical heat revenue (£/yr); 9. System P&L!B29 - Heat utilisation (%)
A24: Theoretical heat revenue (£/yr) | B24: =B23*B21*B20/1000 | C24: kWth × hours ÷ 1000 × £/MWh = £ (if buyer absorbed all) | F24: Calculate max heat income potential | G24: Calculated from upstream values for Theoretical heat revenue (£/yr) | H24: 9. System P&L!B30 - Lost heat revenue (£/yr)
A26: Actual buyer absorption (kWth) | B26: ='5. Buyer Profile'!B49 | C26: Limited by buyer heat demand | F26: Pull actual heat buyer takes | G26: Pulls value from 5. Buyer Profile!B47 | H26: 9. System P&L!B27 - ACTUAL HEAT REVENUE (£/yr); 9. System P&L!B29 - Heat utilisation (%)
A27: ACTUAL HEAT REVENUE (£/yr) | B27: =B26*B21*B20/1000 | C27: kWth × hours ÷ 1000 × £/MWh = £ | F27: Calculate realised heat income | G27: Calculated from upstream values for ACTUAL HEAT REVENUE (£/yr) | H27: 9. System P&L!B30 - Lost heat revenue (£/yr); 9. System P&L!B34 - Heat revenue (£/yr)
A29: Heat utilisation (%) | B29: =IF(B23>0,B26/B23,0) | C29: Actual absorption ÷ theoretical output | F29: Measure heat sales efficiency | G29: Conditional logic for Heat utilisation (%) | H29: 9. System P&L!B53 - Heat utilisation efficiency (%)
A30: Lost heat revenue (£/yr) | B30: =B24-B27 | C30: Foregone income from excess heat - key efficiency metric | F30: Quantify revenue lost to rejection | G30: Calculated from upstream values for Lost heat revenue (£/yr) | H30: 9. System P&L!B54 - Revenue lost to heat rejection (£/y...
A32: TOTAL REVENUE
A33: Compute revenue (£/yr) | B33: =B17 | F33: Financial input or calculation | G33: Formula: Compute revenue (£/yr) | H33: 9. System P&L!B35 - TOTAL REVENUE (£/yr)
A34: Heat revenue (£/yr) | B34: =B27 | F34: Financial input or calculation | G34: Formula: Heat revenue (£/yr) | H34: 9. System P&L!B35 - TOTAL REVENUE (£/yr); 9. System P&L!B36 - Heat as % of total revenue
A35: TOTAL REVENUE (£/yr) | B35: =B33+B34 | F35: Sum all revenue streams | G35: Calculated from upstream values for TOTAL REVENUE (£/yr) | H35: 9. System P&L!B36 - Heat as % of total revenue; 9. System P&L!B45 - Gross profit (£/yr); 9. System P&L!B46 - Gross margin (%)
A36: Heat as % of total revenue | B36: =IF(B35>0,B34/B35,0) | C36: Contribution of heat sales to total revenue | F36: Sum all revenue streams | G36: Conditional logic for Heat as % of total revenue
A38: OPERATING COSTS
A39: Base system opex (£/yr) | B39: ='7. System Opex'!B23 | C39: Module opex + shared overhead (excl. rejection) | F39: Pull core operating costs | G39: Pulls value from 7. System Opex!B23
A40: Heat rejection opex (£/yr) | B40: ='7. System Opex'!B28 | C40: Cost to reject excess heat | F40: Pull rejection operating costs | G40: Pulls value from 7. System Opex!B28 | H40: 9. System P&L!B55 - Cost of heat rejection (£/yr)
A41: Hydraulic augmentation opex (£/yr) | B41: ='7. System Opex'!B35 | F41: Pull pump operating costs | G41: Pulls value from 7. System Opex!B35
A42: TOTAL OPEX (£/yr) | B42: ='7. System Opex'!B37 | F42: Sum all operating costs | G42: Pulls value from 7. System Opex!B37 | H42: 9. System P&L!B45 - Gross profit (£/yr)
A44: PROFIT & RETURNS
A45: Gross profit (£/yr) | B45: =B35-B42 | C45: Total revenue - Total opex | F45: Calculate operating profit | G45: Calculated from upstream values for Gross profit (£/yr) | H45: 9. System P&L!B46 - Gross margin (%); 9. System P&L!B49 - Simple payback (years); 9. System P&L!B50 - Unlevered ROI (%); 9. System P&L!B57 - Heat inefficiency as % of potential...
A46: Gross margin (%) | B46: =IF(B35>0,B45/B35,0) | C46: Gross profit ÷ Total revenue | F46: Calculate profit percentage | G46: Conditional logic for Gross margin (%)
A48: Total system capex (£) | B48: ='6. System Capex'!B46 | F48: Pull investment requirement | G48: Pulls value from 6. System Capex!B46 | H48: 9. System P&L!B49 - Simple payback (years); 9. System P&L!B50 - Unlevered ROI (%)
A49: Simple payback (years) | B49: =IF(B45>0,B48/B45,0) | C49: Capex ÷ Annual profit (ignores time value of money) | F49: Calculate investment recovery time | G49: Conditional logic for Simple payback (years)
A50: Unlevered ROI (%) | B50: =IF(B48>0,B45/B48,0) | C50: Annual profit ÷ Capex | F50: Calculate return on investment | G50: Conditional logic for Unlevered ROI (%)
A52: EFFICIENCY METRICS
A53: Heat utilisation efficiency (%) | B53: =B29 | C53: Proportion of generated heat actually sold | F53: Measure heat sales efficiency | G53: Formula: Heat utilisation efficiency (%)
A54: Revenue lost to heat rejection (£/yr) | B54: =B30 | C54: Foregone heat revenue due to oversizing | F54: Quantify rejection revenue impact | G54: Formula: Revenue lost to heat rejection (£/yr) | H54: 9. System P&L!B56 - Total heat inefficiency cost (£/yr)
A55: Cost of heat rejection (£/yr) | B55: =B40 | C55: Opex to reject unsold heat | F55: Quantify rejection cost impact | G55: Formula: Cost of heat rejection (£/yr) | H55: 9. System P&L!B56 - Total heat inefficiency cost (£/yr)
A56: Total heat inefficiency cost (£/yr) | B56: =B54+B55 | C56: Lost revenue + rejection cost = true cost of thermal mismatch | F56: Sum heat-related losses | G56: Calculated from upstream values for Total heat inefficiency cost (£/yr) | H56: 9. System P&L!B57 - Heat inefficiency as % of potential...
A57: Heat inefficiency as % of potential profit | B57: =IF((B45+B56)>0,B56/(B45+B56),0) | C57: Shows how much profit is eroded by thermal mismatch | F57: Show heat loss as share of potential | G57: Conditional logic for Heat inefficiency as % of potential profit

Sheet 11. Reference Data
A1: REFERENCE DATA | F1: Intent | G1: Explanation | H1: Dependents
A2: Lookup tables and assumptions used throughout the model | F2: Model parameter | G2: Row label only
A3: Yellow cells are adjustable inputs | F3: Model parameter | G3: Row label only
A5: HEAT REJECTION INFRASTRUCTURE
A6: Equipment selection based on total system thermal output (worst-case sizing) | F6: Reference cost for thermal equipment | G6: Row label only
A7: Operating costs based on actual excess heat rejected | F7: Financial input or calculation | G7: Row label only
A9: Method | B9: Capacity Range | C9: Capex (£/kWth) | D9: Opex (£/kWth/yr) | E9: Notes | F9: Model parameter | G9: Text value for Method
A10: Dry cooler | B10: <100 kWth | C10: 150 | D10: 70 | E10: Air-cooled, no water consumption. Limited by ambient temp on hot days. | F10: Reference cost for rejection equipment | G10: Text value for Dry cooler
A11: Adiabatic cooler | B11: 100-499 kWth | C11: 220 | D11: 110 | E11: Spray-assisted cooling. Higher capex, water consumption adds to opex. | F11: Reference cost for rejection equipment | G11: Text value for Adiabatic cooler
A12: Cooling tower | B12: ≥500 kWth | C12: 180 | D12: 95 | E12: Evaporative cooling. Most efficient at scale, requires water treatment. | F12: Reference cost for rejection equipment | G12: Text value for Cooling tower
A14: Capacity Thresholds | F14: Reference decision boundary value | G14: Row label only
A15: Dry cooler max (kWth) | B15: 100 | F15: Reference cost for rejection equipment | G15: Input parameter: Dry cooler max (kWth) | H15: 5. Buyer Profile!B51 - Rejection method
A16: Adiabatic cooler max (kWth) | B16: 500 | F16: Reference cost for rejection equipment | G16: Input parameter: Adiabatic cooler max (kWth) | H16: 5. Buyer Profile!B51 - Rejection method
A19: COOLING METHOD CHARACTERISTICS
A20: Performance and cost characteristics by liquid cooling approach | F20: Financial input or calculation | G20: Row label only
A22: Cooling Method | B22: Heat Capture | C22: Capture Temp | D22: Capex Premium | E22: Source ΔT (°C) | F22: Model parameter | G22: Text value for Cooling Method
A23: Direct-to-Chip (DTC) | B23: 75% | C23: 57.5°C | D23: +15% | E23: 10 | F23: Model parameter | G23: Text value for Direct-to-Chip (DTC)
A24: Single-Phase Immersion | B24: 95% | C24: 50°C | D24: +25% | E24: 6 | F24: Reference cost for immersion equipment | G24: Text value for Single-Phase Immersion
A25: Two-Phase Immersion | B25: 98% | C25: 55°C | D25: +40% | E25: 3 | F25: Reference cost for immersion equipment | G25: Text value for Two-Phase Immersion
A26: Rear Door Heat Exchanger | B26: 50% | C26: 45°C | D26: +10% | E26: 12 | F26: Reference cost for thermal equipment | G26: Text value for Rear Door Heat Exchanger
A27: Air Cooled (Reference) | B27: 5% | C27: 35°C | D27: 0% | E27: 15 | F27: Model parameter | G27: Text value for Air Cooled (Reference)
A30: CHIPSET SPECIFICATIONS
A31: GPU specifications by model | F31: Model parameter | G31: Row label only
A33: Chipset | B33: TDP (W) | C33: Chips/Server | D33: T_junction (°C) | E33: Notes | F33: Model parameter | G33: Text value for Chipset
A34: NVIDIA H100 | B34: 700 | C34: 8 | D34: 83 | E34: Current gen. DTC reference design available. | F34: Reference specs for NVIDIA H100 | G34: Section header
A35: NVIDIA H200 | B35: 700 | C35: 8 | D35: 83 | E35: H100 + HBM3e memory upgrade. Same thermal. | F35: Reference specs for NVIDIA H200 | G35: Section header
A36: NVIDIA B200 | B36: 1000 | C36: 8 | D36: 85 | E36: Blackwell. Higher TDP, higher capture temps expected. | F36: Reference specs for NVIDIA B200 | G36: Section header
A37: AMD MI300X | B37: 750 | C37: 8 | D37: 90 | E37: Instinct series. Competitive with H100. | F37: Reference specs for AMD MI300X | G37: Section header
A38: Intel Gaudi 3 | B38: 600 | C38: 8 | D38: 95 | E38: AI accelerator. Lower TDP. | F38: Model parameter | G38: Input parameter: Intel Gaudi 3
A41: HEAT PUMP ECONOMICS
A42: COP and operating cost by temperature lift | F42: Reference heat pump efficiency parameters | G42: Row label only
A44: Target delivery temp (°C) | B44: 75 | C44: Reference COPs at this delivery temp (using η from row 110) | F44: Temperature parameter for thermal design | G44: Input parameter: Target delivery temp (°C) | H44: 11. Reference Data!B47 - 57.5; 11. Reference Data!C47 - 57.5; 11. Reference Data!B48 - 50; 11. Reference Data!C48 - 50; 11. Reference Data!B49 - 55; 11. Reference Data!C49 - 55; 11. Reference Data!B50 - 45; 11. Reference Data!C50 - 45
A46: Source Temp (°C) | B46: Lift (°C) | C46: Est. COP | D46: kWe per kWth | E46: Cooling Method | F46: Temperature parameter for thermal design | G46: Text value for Source Temp (°C)
A47: 57.5 | B47: =B44-A47 | C47: =ROUND(B110*(B44+273.15)/B47,1) | D47: =ROUND(1/C47,3) | E47: DTC | F47: Model parameter | G47: Calculated from upstream values for 57.5 | H47: 11. Reference Data!C47 - 57.5
A48: 50 | B48: =B44-A48 | C48: =ROUND(B110*(B44+273.15)/B48,1) | D48: =ROUND(1/C48,3) | E48: Single-Phase Immersion | F48: Model parameter | G48: Calculated from upstream values for 50 | H48: 11. Reference Data!C48 - 50
A49: 55 | B49: =B44-A49 | C49: =ROUND(B110*(B44+273.15)/B49,1) | D49: =ROUND(1/C49,3) | E49: Two-Phase Immersion | F49: Model parameter | G49: Calculated from upstream values for 55 | H49: 11. Reference Data!C49 - 55
A50: 45 | B50: =B44-A50 | C50: =ROUND(B110*(B44+273.15)/B50,1) | D50: =ROUND(1/C50,3) | E50: RDHX | F50: Model parameter | G50: Calculated from upstream values for 45 | H50: 11. Reference Data!C50 - 45
A53: PROCESS ΔT REFERENCE
A54: Temperature differential by industrial process (affects flow requirements) | F54: Temperature parameter for thermal design | G54: Row label only
A56: Process | B56: Typical ΔT (°C) | C56: Constraint Type | D56: Source | F56: Model parameter | G56: Text value for Process
A57: Pasteurisation | B57: 5 | C57: Flow-constrained | D57: Tetra Pak | F57: Model parameter | G57: Input parameter: Pasteurisation
A58: Swimming pools | B58: 5 | C58: Flow-constrained | D58: Kensa | F58: Model parameter | G58: Input parameter: Swimming pools
A59: Building HVAC | B59: 10 | C59: Balanced | D59: ASHRAE 90.1 | F59: Model parameter | G59: Input parameter: Building HVAC
A60: CIP systems | B60: 12 | C60: Balanced | D60: CSI Designs | F60: Model parameter | G60: Input parameter: CIP systems
A61: Commercial laundry | B61: 18 | C61: Thermal-constrained | D61: AERCO | F61: Model parameter | G61: Input parameter: Commercial laundry
A62: District heating | B62: 30 | C62: Thermal-constrained | D62: CIBSE CP1 | F62: Model parameter | G62: Input parameter: District heating
A65: MODULE HARDWARE CAPEX
A66: Itemised costs for module components - yellow cells are adjustable inputs | F66: Financial input or calculation | G66: Row label only
A68: Component | B68: Cost (£) | C68: Unit | D68: Scaling Basis | E68: Source | F68: Model parameter | G68: Text value for Component
A70: ENCLOSURE & STRUCTURE | G70: Row label only
A71: Container shell (40ft) | B71: 35000 | C71: per module | D71: Fixed | E71: Industry average | F71: Reference cost for enclosure | G71: Input assumption: Container shell (40ft) | H71: 2. Module Capex!B13 - Container shell
A72: Container fit-out (electrical, HVAC prep) | B72: 25000 | C72: per module | D72: Fixed | E72: Industry average | F72: Reference cost for enclosure | G72: Input assumption: Container fit-out (electrical, HVAC prep) | H72: 2. Module Capex!B14 - Container fit-out
A73: Rack enclosure (42U enclosed) | B73: 2000 | C73: per rack | D73: Rack count | E73: CDW/RackSolutions | F73: Reference cost per rack | G73: Input assumption: Rack enclosure (42U enclosed) | H73: 2. Module Capex!B15 - Rack enclosures; 2. Module Capex!C15 - Rack enclosures
A75: DTC COOLING COMPONENTS | G75: Row label only
A76: Cold plate kit (per server) | B76: 250 | C76: per server | D76: Server count | E76: CoolIT/Asetek | F76: Reference cost for DTC equipment | G76: Input parameter: Cold plate kit (per server) | H76: 2. Module Capex!B19 - Cold plate kits
A77: CDU (Coolant Distribution Unit) | B77: 35000 | C77: per module | D77: Fixed base | E77: Vertiv/Schneider | F77: Reference cost for DTC equipment | G77: Input assumption: CDU (Coolant Distribution Unit) | H77: 2. Module Capex!B20 - CDU (base)
A78: CDU capacity scaling | B78: 80 | C78: per kW | D78: Module IT kW | E78: Industry estimate | F78: Reference cost for DTC equipment | G78: Input parameter: CDU capacity scaling | H78: 2. Module Capex!B21 - CDU (capacity scaling)
A79: Manifolds & quick-connects | B79: 150 | C79: per server | D79: Server count | E79: Industry estimate | F79: Reference cost for DTC equipment | G79: Input parameter: Manifolds & quick-connects | H79: 2. Module Capex!B22 - Manifolds & quick-connects
A80: Primary loop piping | B80: 5000 | C80: per module | D80: Fixed | E80: Industry estimate | F80: Model parameter | G80: Input assumption: Primary loop piping | H80: 2. Module Capex!B23 - Primary loop piping
A82: IMMERSION COOLING COMPONENTS | G82: Row label only
A83: Single-phase immersion tank | B83: 28000 | C83: per rack | D83: Rack count | E83: GRC/LiquidCool | F83: Reference cost for immersion equipment | G83: Input assumption: Single-phase immersion tank | H83: 2. Module Capex!B27 - Immersion tanks
A84: Two-phase immersion tank | B84: 45000 | C84: per rack | D84: Rack count | E84: LiquidStack/Asperitas | F84: Reference cost for immersion equipment | G84: Input assumption: Two-phase immersion tank | H84: 2. Module Capex!B27 - Immersion tanks
A85: Dielectric fluid - single-phase | B85: 12 | C85: per litre | D85: Tank volume | E85: Shell/Cargill | F85: Reference cost for immersion equipment | G85: Input parameter: Dielectric fluid - single-phase | H85: 2. Module Capex!B28 - Dielectric fluid (initial fill)
A86: Dielectric fluid - two-phase | B86: 120 | C86: per litre | D86: Tank volume | E86: 3M Novec | F86: Reference cost for immersion equipment | G86: Input parameter: Dielectric fluid - two-phase | H86: 2. Module Capex!B28 - Dielectric fluid (initial fill)
A87: Fluid volume per rack (single-phase) | B87: 600 | C87: litres | D87: Per rack | E87: Industry average | F87: Reference cost per rack | G87: Input parameter: Fluid volume per rack (single-phase) | H87: 2. Module Capex!B28 - Dielectric fluid (initial fill)
A88: Fluid volume per rack (two-phase) | B88: 400 | C88: litres | D88: Per rack | E88: Industry average | F88: Reference cost per rack | G88: Input parameter: Fluid volume per rack (two-phase) | H88: 2. Module Capex!B28 - Dielectric fluid (initial fill)
A89: Fluid management system | B89: 15000 | C89: per module | D89: Fixed | E89: Industry estimate | F89: Reference fluid cost or volume | G89: Input assumption: Fluid management system | H89: 2. Module Capex!B29 - Fluid management system
A91: POWER DISTRIBUTION | G91: Row label only
A92: High-density PDU (per rack) | B92: 3000 | C92: per rack | D92: Rack count | E92: Vertiv/Raritan | F92: Reference cost per rack | G92: Input assumption: High-density PDU (per rack) | H92: 2. Module Capex!B33 - Rack PDUs
A93: Module power distribution | B93: 180 | C93: per kW | D93: Module IT kW | E93: Schneider Electric | F93: Reference cost for electrical equipment | G93: Input parameter: Module power distribution | H93: 2. Module Capex!B34 - Module power distribution
A94: Electrical panels & switchgear | B94: 20000 | C94: per module | D94: Fixed | E94: Industry estimate | F94: Reference cost for electrical equipment | G94: Input assumption: Electrical panels & switchgear | H94: 2. Module Capex!B35 - Electrical panels & switchgear
A96: THERMAL INTEGRATION | G96: Row label only
A97: Primary heat exchanger | B97: 12000 | C97: per module | D97: Fixed base | E97: Alfa Laval/SWEP | F97: Reference cost for thermal equipment | G97: Input assumption: Primary heat exchanger | H97: 2. Module Capex!B39 - Primary heat exchanger (base)
A98: Heat exchanger scaling | B98: 25 | C98: per kW | D98: Module thermal kW | E98: Industry estimate | F98: Reference cost for thermal equipment | G98: Input parameter: Heat exchanger scaling | H98: 2. Module Capex!B40 - Heat exchanger (capacity scaling)
A99: Thermal integration skid (pumps, valves) | B99: 18000 | C99: per module | D99: Fixed | E99: Industry estimate | F99: Reference cost for thermal equipment | G99: Input assumption: Thermal integration skid (pumps, valves) | H99: 2. Module Capex!B41 - Thermal integration skid
A100: Instrumentation & sensors | B100: 8000 | C100: per module | D100: Fixed | E100: Industry estimate | F100: Reference cost for monitoring equipment | G100: Input assumption: Instrumentation & sensors | H100: 2. Module Capex!B42 - Instrumentation & sensors
A102: MONITORING & CONTROLS | G102: Row label only
A103: BMS base system | B103: 18000 | C103: per module | D103: Fixed | E103: Schneider/Honeywell | F103: Reference cost for monitoring equipment | G103: Input assumption: BMS base system | H103: 2. Module Capex!B46 - BMS base system
A104: Per-rack monitoring | B104: 500 | C104: per rack | D104: Rack count | E104: Industry estimate | F104: Reference cost per rack | G104: Input parameter: Per-rack monitoring | H104: 2. Module Capex!B47 - Per-rack monitoring
A105: Network infrastructure | B105: 8000 | C105: per module | D105: Fixed | E105: Industry estimate | F105: Reference cost for network equipment | G105: Input assumption: Network infrastructure | H105: 2. Module Capex!B48 - Network infrastructure
A108: HEAT PUMP EFFICIENCY MODEL
A109: Carnot-based COP model with configurable efficiency factor | F109: Reference heat pump efficiency parameters | G109: Row label only
A110: Carnot efficiency factor (η) | B110: 0.45 | C110: Conservative default (range: 0.40-0.55 per NREL) | F110: Reference heat pump efficiency parameters | G110: Input parameter: Carnot efficiency factor (η) | H110: 0. Rack Profile!B52 - Estimated COP at recommended output; 0. Rack Profile!B61 - COP at this lift; 1. Module Criteria!B17 - Heat pump COP; 11. Reference Data!C47 - 57.5; 11. Reference Data!C48 - 50; 11. Reference Data!C49 - 55; 11. Reference Data!C50 - 45
A111: Minimum practical COP | B111: 2 | C111: Floor to prevent unrealistic values | F111: Reference heat pump efficiency parameters | G111: Input parameter: Minimum practical COP | H111: 0. Rack Profile!B52 - Estimated COP at recommended output; 0. Rack Profile!B61 - COP at this lift; 1. Module Criteria!B17 - Heat pump COP
A112: Maximum practical COP | B112: 8 | C112: Ceiling to prevent unrealistic values | F112: Reference heat pump efficiency parameters | G112: Input parameter: Maximum practical COP | H112: 0. Rack Profile!B52 - Estimated COP at recommended output; 0. Rack Profile!B61 - COP at this lift; 1. Module Criteria!B17 - Heat pump COP
A114: Formula: COP = η × T_hot(K) / (T_hot - T_cold) | F114: Reference heat pump efficiency parameters | G114: Row label only
A115: Where T in Kelvin = T in °C + 273.15 | F115: Model parameter | G115: Row label only
A117: HYDRAULIC AUGMENTATION RATES
A118: For flow deficit handling when buyer flow > module flow | F118: Fluid flow parameter for hydraulic design | G118: Row label only
A120: Augmentation pump capex (£ per m³/hr) | B120: 150 | C120: Centrifugal pump sized for flow deficit | F120: Reference pump specifications or cost | G120: Input parameter: Augmentation pump capex (£ per m³/hr) | H120: 6. System Capex!B37 - Augmentation pump capex
A121: Augmentation pump power (kW per m³/hr) | B121: 0.1 | C121: At ~25m head typical for HVAC systems | F121: Reference cost for electrical equipment | G121: Input parameter: Augmentation pump power (kW per m³/hr) | H121: 5. Buyer Profile!B83 - Augmentation pump power (kW)
A122: Mixing valve + controls (£) | B122: 2500 | C122: 3-way valve with actuator and controller | F122: Reference hydraulic equipment cost | G122: Input assumption: Mixing valve + controls (£) | H122: 6. System Capex!B38 - Mixing valve + controls
A123: Pipe upsizing allowance (£ per m³/hr) | B123: 50 | C123: Applied when flow deficit > 20 m³/hr | F123: Reference hydraulic equipment cost | G123: Input parameter: Pipe upsizing allowance (£ per m³/hr) | H123: 6. System Capex!B39 - Pipe upsizing allowance
A124: Standard augmentation pump capacity (m³/hr) | B124: 25 | C124: Typical centrifugal pump rating for HVAC | F124: Reference pump specifications or cost | G124: Input parameter: Standard augmentation pump capacity (m³/hr) | H124: 5. Buyer Profile!B84 - Augmentation pumps required; 5. Buyer Profile!B85 - Augmentation pump capacity (m³/hr); 6. System Capex!B37 - Augmentation pump capex

Sheet 12. Process Library
A1: PROCESS LIBRARY
A2: Reference data for industrial heat demand profiles
A3: Process | B3: Size | C3: Temp (°C) | D3: Load (kWth) | E3: Hrs/yr | F3: Notes | G3: Dropdown Name | H3: Source | I3: ΔT (°C) | J3: Source URL
A4: Pasteurisation | B4: Small | C4: 72 | D4: 65 | E4: 4000 | F4: Craft dairy/microbrewery (5,000 L/day) | G4: Pasteurisation - Small | H4: Tetra Pak Dairy Processing Handbook | I4: 5 | J4: https://dairyprocessinghandbook.tetrapak.com/chapter/heat-exchangers
A5: Pasteurisation | B5: Medium | C5: 72 | D5: 500 | E5: 5500 | F5: Regional dairy (50,000 L/day) | G5: Pasteurisation - Medium | H5: Tetra Pak Dairy Processing Handbook | I5: 5 | J5: https://dairyprocessinghandbook.tetrapak.com/chapter/heat-exchangers
A6: Pasteurisation | B6: Large | C6: 72 | D6: 2500 | E6: 7000 | F6: Industrial dairy (250,000+ L/day) | G6: Pasteurisation - Large | H6: Tetra Pak Dairy Processing Handbook | I6: 5 | J6: https://dairyprocessinghandbook.tetrapak.com/chapter/heat-exchangers
A7: CIP (Clean-in-Place) | B7: Small | C7: 85 | D7: 50 | E7: 3000 | F7: Single vessel/tank system | G7: CIP (Clean-in-Place) - Small | H7: CSI Designs - Heat Exchangers in CIP | I7: 12 | J7: https://www.csidesigns.com/blog/articles/how-heat-exchangers-work-during-clean-in-place
A8: CIP (Clean-in-Place) | B8: Medium | C8: 85 | D8: 150 | E8: 4000 | F8: Multi-tank dairy/brewery | G8: CIP (Clean-in-Place) - Medium | H8: CSI Designs - Heat Exchangers in CIP | I8: 12 | J8: https://www.csidesigns.com/blog/articles/how-heat-exchangers-work-during-clean-in-place
A9: CIP (Clean-in-Place) | B9: Large | C9: 85 | D9: 400 | E9: 5000 | F9: Full processing plant | G9: CIP (Clean-in-Place) - Large | H9: CSI Designs - Heat Exchangers in CIP | I9: 12 | J9: https://www.csidesigns.com/blog/articles/how-heat-exchangers-work-during-clean-in-place
A10: Bottle washing | B10: Small | C10: 80 | D10: 35 | E10: 4000 | F10: Craft bottling line | G10: Bottle washing - Small | H10: GEA Brewing Systems | I10: 10 | J10: https://www.gea.com/en/products/brewery-systems
A11: Bottle washing | B11: Medium | C11: 80 | D11: 120 | E11: 5500 | F11: Regional bottler (10k bottles/hr) | G11: Bottle washing - Medium | H11: GEA Brewing Systems | I11: 10 | J11: https://www.gea.com/en/products/brewery-systems
A12: Bottle washing | B12: Large | C12: 80 | D12: 280 | E12: 7000 | F12: Industrial (50k+ bottles/hr) | G12: Bottle washing - Large | H12: GEA Brewing Systems | I12: 10 | J12: https://www.gea.com/en/products/brewery-systems
A13: Parts degreasing | B13: Small | C13: 60 | D13: 25 | E13: 3000 | F13: Workshop/small batch | G13: Parts degreasing - Small | H13: Dürr Systems AG | I13: 15 | J13: https://www.durr.com/en/products-and-services/cleaning-technology
A14: Parts degreasing | B14: Medium | C14: 60 | D14: 75 | E14: 4500 | F14: Automotive supplier | G14: Parts degreasing - Medium | H14: Dürr Systems AG | I14: 15 | J14: https://www.durr.com/en/products-and-services/cleaning-technology
A15: Parts degreasing | B15: Large | C15: 60 | D15: 180 | E15: 6000 | F15: Heavy manufacturing | G15: Parts degreasing - Large | H15: Dürr Systems AG | I15: 15 | J15: https://www.durr.com/en/products-and-services/cleaning-technology
... A45: Fermentation | B45: Large | C45: 35 | D45: 280 | E45: 8000 | F45: Industrial biotech | G45: Fermentation - Large | H45: Clarke Energy / Brewery Best Practice | I45: 5 | J45: https://www.clarke-energy.com/applications/breweries/
A48: MODULE MATCHING SUMMARY
A49: Single 250kWth module best matches:
A50: • Pasteurisation - Small/Medium
A51: • CIP - All sizes
A52: • Bottle washing - All sizes
A53: • Parts degreasing - All sizes
A54: • Commercial laundry - Small
A55: • Timber drying - Small/Medium
A56: • Paint curing - All sizes
A57: • Textile drying - Small/Medium
A58: • Building HVAC - Small/Medium
A59: • Swimming pool - All sizes
... A65: SOURCE REFERENCES
A66: AHDB Horticulture | B66: UK Agriculture & Horticulture Development Board - Glasshouse energy benchmarks
A67: Alfa Laval CIP Systems | B67: Industrial CIP system specifications and energy requirements
A68: ΔT SOURCE REFERENCES | B68: Timber drying technology handbook
A69: CIBSE Guide A/B | B69: UK Chartered Institution of Building Services Engineers design guides
A70: Process Type | B70: ΔT (°C) | C70: Source | D70: URL
A71: Pasteurisation | B71: 5 | C71: Tetra Pak Dairy Processing Handbook | D71: https://dairyprocessinghandbook.tetrapak.com/chapter/heat-exchangers
A72: CIP (Clean-in-Place) | B72: 12 | C72: CSI Designs - Heat Exchangers in CIP | D72: https://www.csidesigns.com/blog/articles/how-heat-exchangers-work-during-clean-in-place
A73: Bottle washing | B73: 10 | C73: GEA Brewing Systems | D73: https://www.gea.com/en/products/brewery-systems
A74: Parts degreasing | B74: 15 | C74: Dürr Systems AG | D74: https://www.durr.com/en/products-and-services/cleaning-technology
A75: Commercial laundry | B75: 18 | C75: AERCO Laundry Sizing Guide | D75: https://www.aerco.com/dfsmedia/0533dbba17714b1ab581ab07a4cbb521/58930-source/sizing-laundry-hot-water-systems
A76: Timber drying | B76: 18 | C76: Oklahoma State Extension - Kiln Drying | D76: https://extension.okstate.edu/fact-sheets/fundamental-aspects-of-kiln-drying-lumber.html
A77: Paint curing | B77: 15 | C77: Dürr Paint Systems | D77: https://www.durr.com/en/products-and-services/paint-systems
A78: Textile drying | B78: 20 | C78: Monforts Textilmaschinen | D78: https://www.monforts.de/en/
A79: District heating | B79: 30 | C79: CIBSE CP1 Heat Networks Code of Practice | D79: https://www.cibsejournal.com/technical/the-perfect-return-heat-network-return-temperatures/
A80: Building HVAC | B80: 12 | C80: ASHRAE 90.1 / CIBSE Guide B | D80: https://www.trane.com/content/dam/Trane/Commercial/global/products-systems/education-training/engineers-newsletters/standards-codes/ADM-APN070-EN_06032019.pdf
A81: Swimming pool | B81: 5 | C81: Kensa Heat Pumps - Pools Application Guide | D81: https://www.kensaheatpumps.com/wp-content/uploads/2014/09/AIS—Heat-pumps-and-swimming-pools-—2.0_with_metadata.pdf
A82: Glasshouse heating | B82: 20 | C82: Dutch Greenhouses / AHDB Horticulture | D82: https://dutchgreenhouses.com/en/climate/heating
... A84: Fermentation | B84: 5 | C84: Clarke Energy / Brewery Best Practice | D84: https://www.clarke-energy.com/applications/breweries/
A87: NOTES ON ΔT VALUES
A88: • ΔT = temperature difference between supply and return water in the process heat loop
A89: • Lower ΔT (5°C) = tight temperature control required, higher flow rate needed
A90: • Higher ΔT (30°C) = wider temperature tolerance, lower flow rate acceptable
A91: • Flow rate (m³/hr) = Thermal load (kW) / (4.18 × ΔT) × 3.6
A92: • A process with ΔT=5°C needs 6× the flow rate of one with ΔT=30°C for same thermal load
